{"installation": "ff179504-04ae-45bc-9cf1-b6a5cb111cf7", "band_ndx": 26, "create_time": 1596621387, "observations": [{"peaker": 0, "moving_average": 71, "time_stamp": 1596619374, "frequency": 4600000, "modulation": "NFM", "strength": 71}, {"peaker": 0, "moving_average": 71, "time_stamp": 1596619379, "frequency": 4600125, "modulation": "NFM", "strength": 71}, {"peaker": 0, "moving_average": 71, "time_stamp": 1596619384, "frequency": 4600250, "modulation": "NFM", "strength": 73}, {"peaker": 0, "moving_average": 71, "time_stamp": 1596619389, "frequency": 4600375, "modulation": "NFM", "strength": 70}, {"peaker": 0, "moving_average": 69, "time_stamp": 1596619394, "frequency": 4600500, "modulation": "NFM", "strength": 62}, {"peaker": 0, "moving_average": 68, "time_stamp": 1596619399, "frequency": 4600625, "modulation": "NFM", "strength": 61}, {"peaker": 0, "moving_average": 67, "time_stamp": 1596619404, "frequency": 4600750, "modulation": "NFM", "strength": 64}, {"peaker": 0, "moving_average": 67, "time_stamp": 1596619409, "frequency": 4600875, "modulation": "NFM", "strength": 69}, {"peaker": 0, "moving_average": 68, "time_stamp": 1596619414, "frequency": 4601000, "modulation": "NFM", "strength": 76}, {"peaker": 0, "moving_average": 68, "time_stamp": 1596619419, "frequency": 4601125, "modulation": "NFM", "strength": 68}, {"peaker": 0, "moving_average": 69, "time_stamp": 1596619424, "frequency": 4601250, "modulation": "NFM", "strength": 77}, {"peaker": 0, "moving_average": 69, "time_stamp": 1596619429, "frequency": 4601375, "modulation": "NFM", "strength": 67}, {"peaker": 0, "moving_average": 69, "time_stamp": 1596619434, "frequency": 4601500, "modulation": "NFM", "strength": 68}, {"peaker": 0, "moving_average": 69, "time_stamp": 1596619439, "frequency": 4601625, "modulation": "NFM", "strength": 69}, {"peaker": 0, "moving_average": 69, "time_stamp": 1596619444, "frequency": 4601750, "modulation": "NFM", "strength": 69}, {"peaker": 0, "moving_average": 69, "time_stamp": 1596619449, "frequency": 4601875, "modulation": "NFM", "strength": 77}, {"peaker": 0, "moving_average": 69, "time_stamp": 1596619454, "frequency": 4602000, "modulation": "NFM", "strength": 70}, {"peaker": 0, "moving_average": 69, "time_stamp": 1596619459, "frequency": 4602125, "modulation": "NFM", "strength": 70}, {"peaker": 0, "moving_average": 69, "time_stamp": 1596619464, "frequency": 4602250, "modulation": "NFM", "strength": 71}, {"peaker": 0, "moving_average": 69, "time_stamp": 1596619469, "frequency": 4602375, "modulation": "NFM", "strength": 69}, {"peaker": 0, "moving_average": 69, "time_stamp": 1596619474, "frequency": 4602500, "modulation": "NFM", "strength": 77}, {"peaker": 0, "moving_average": 70, "time_stamp": 1596619479, "frequency": 4602625, "modulation": "NFM", "strength": 77}, {"peaker": 0, "moving_average": 70, "time_stamp": 1596619484, "frequency": 4602750, "modulation": "NFM", "strength": 71}, {"peaker": 0, "moving_average": 70, "time_stamp": 1596619490, "frequency": 4602875, "modulation": "NFM", "strength": 68}, {"peaker": 0, "moving_average": 70, "time_stamp": 1596619495, "frequency": 4603000, "modulation": "NFM", "strength": 80}, {"peaker": 0, "moving_average": 70, "time_stamp": 1596619500, "frequency": 4603125, "modulation": "NFM", "strength": 71}, {"peaker": 0, "moving_average": 70, "time_stamp": 1596619505, "frequency": 4603250, "modulation": "NFM", "strength": 70}, {"peaker": 0, "moving_average": 70, "time_stamp": 1596619510, "frequency": 4603375, "modulation": "NFM", "strength": 66}, {"peaker": 0, "moving_average": 70, "time_stamp": 1596619515, "frequency": 4603500, "modulation": "NFM", "strength": 70}, {"peaker": 0, "moving_average": 70, "time_stamp": 1596619520, "frequency": 4603625, "modulation": "NFM", "strength": 70}, {"peaker": 0, "moving_average": 70, "time_stamp": 1596619525, "frequency": 4603750, "modulation": "NFM", "strength": 66}, {"peaker": 0, "moving_average": 70, "time_stamp": 1596619530, "frequency": 4603875, "modulation": "NFM", "strength": 69}, {"peaker": 0, "moving_average": 70, "time_stamp": 1596619535, "frequency": 4604000, "modulation": "NFM", "strength": 72}, {"peaker": 0, "moving_average": 70, "time_stamp": 1596619540, "frequency": 4604125, "modulation": "NFM", "strength": 69}, {"peaker": 0, "moving_average": 70, "time_stamp": 1596619545, "frequency": 4604250, "modulation": "NFM", "strength": 70}, {"peaker": 0, "moving_average": 70, "time_stamp": 1596619550, "frequency": 4604375, "modulation": "NFM", "strength": 68}, {"peaker": 0, "moving_average": 70, "time_stamp": 1596619555, "frequency": 4604500, "modulation": "NFM", "strength": 70}, {"peaker": 0, "moving_average": 70, "time_stamp": 1596619560, "frequency": 4604625, "modulation": "NFM", "strength": 70}, {"peaker": 0, "moving_average": 70, "time_stamp": 1596619565, "frequency": 4604750, "modulation": "NFM", "strength": 67}, {"peaker": 0, "moving_average": 70, "time_stamp": 1596619570, "frequency": 4604875, "modulation": "NFM", "strength": 69}, {"peaker": 0, "moving_average": 69, "time_stamp": 1596619575, "frequency": 4605000, "modulation": "NFM", "strength": 60}, {"peaker": 0, "moving_average": 69, "time_stamp": 1596619580, "frequency": 4605125, "modulation": "NFM", "strength": 69}, {"peaker": 0, "moving_average": 69, "time_stamp": 1596619585, "frequency": 4605250, "modulation": "NFM", "strength": 76}, {"peaker": 0, "moving_average": 70, "time_stamp": 1596619590, "frequency": 4605375, "modulation": "NFM", "strength": 79}, {"peaker": 0, "moving_average": 70, "time_stamp": 1596619595, "frequency": 4605500, "modulation": "NFM", "strength": 69}, {"peaker": 0, "moving_average": 69, "time_stamp": 1596619600, "frequency": 4605625, "modulation": "NFM", "strength": 62}, {"peaker": 0, "moving_average": 69, "time_stamp": 1596619605, "frequency": 4605750, "modulation": "NFM", "strength": 69}, {"peaker": 0, "moving_average": 69, "time_stamp": 1596619610, "frequency": 4605875, "modulation": "NFM", "strength": 57}, {"peaker": 0, "moving_average": 69, "time_stamp": 1596619615, "frequency": 4606000, "modulation": "NFM", "strength": 77}, {"peaker": 0, "moving_average": 69, "time_stamp": 1596619620, "frequency": 4606125, "modulation": "NFM", "strength": 69}, {"peaker": 0, "moving_average": 69, "time_stamp": 1596619625, "frequency": 4606250, "modulation": "NFM", "strength": 68}, {"peaker": 0, "moving_average": 69, "time_stamp": 1596619630, "frequency": 4606375, "modulation": "NFM", "strength": 73}, {"peaker": 0, "moving_average": 69, "time_stamp": 1596619635, "frequency": 4606500, "modulation": "NFM", "strength": 70}, {"peaker": 0, "moving_average": 69, "time_stamp": 1596619641, "frequency": 4606625, "modulation": "NFM", "strength": 69}, {"peaker": 0, "moving_average": 69, "time_stamp": 1596619646, "frequency": 4606750, "modulation": "NFM", "strength": 69}, {"peaker": 0, "moving_average": 69, "time_stamp": 1596619651, "frequency": 4606875, "modulation": "NFM", "strength": 68}, {"peaker": 0, "moving_average": 69, "time_stamp": 1596619656, "frequency": 4607000, "modulation": "NFM", "strength": 60}, {"peaker": 0, "moving_average": 69, "time_stamp": 1596619661, "frequency": 4607125, "modulation": "NFM", "strength": 70}, {"peaker": 0, "moving_average": 69, "time_stamp": 1596619666, "frequency": 4607250, "modulation": "NFM", "strength": 70}, {"peaker": 0, "moving_average": 69, "time_stamp": 1596619671, "frequency": 4607375, "modulation": "NFM", "strength": 68}, {"peaker": 0, "moving_average": 69, "time_stamp": 1596619676, "frequency": 4607500, "modulation": "NFM", "strength": 70}, {"peaker": 0, "moving_average": 69, "time_stamp": 1596619681, "frequency": 4607625, "modulation": "NFM", "strength": 68}, {"peaker": 0, "moving_average": 69, "time_stamp": 1596619686, "frequency": 4607750, "modulation": "NFM", "strength": 70}, {"peaker": 0, "moving_average": 69, "time_stamp": 1596619691, "frequency": 4607875, "modulation": "NFM", "strength": 72}, {"peaker": 0, "moving_average": 69, "time_stamp": 1596619696, "frequency": 4608000, "modulation": "NFM", "strength": 72}, {"peaker": 0, "moving_average": 69, "time_stamp": 1596619701, "frequency": 4608125, "modulation": "NFM", "strength": 68}, {"peaker": 0, "moving_average": 69, "time_stamp": 1596619706, "frequency": 4608250, "modulation": "NFM", "strength": 76}, {"peaker": 0, "moving_average": 69, "time_stamp": 1596619711, "frequency": 4608375, "modulation": "NFM", "strength": 70}, {"peaker": 0, "moving_average": 69, "time_stamp": 1596619716, "frequency": 4608500, "modulation": "NFM", "strength": 68}, {"peaker": 0, "moving_average": 69, "time_stamp": 1596619721, "frequency": 4608625, "modulation": "NFM", "strength": 74}, {"peaker": 0, "moving_average": 69, "time_stamp": 1596619726, "frequency": 4608750, "modulation": "NFM", "strength": 60}, {"peaker": 0, "moving_average": 69, "time_stamp": 1596619731, "frequency": 4608875, "modulation": "NFM", "strength": 65}, {"peaker": 0, "moving_average": 69, "time_stamp": 1596619736, "frequency": 4609000, "modulation": "NFM", "strength": 70}, {"peaker": 0, "moving_average": 69, "time_stamp": 1596619741, "frequency": 4609125, "modulation": "NFM", "strength": 70}, {"peaker": 0, "moving_average": 69, "time_stamp": 1596619746, "frequency": 4609250, "modulation": "NFM", "strength": 60}, {"peaker": 0, "moving_average": 69, "time_stamp": 1596619751, "frequency": 4609375, "modulation": "NFM", "strength": 68}, {"peaker": 0, "moving_average": 69, "time_stamp": 1596619756, "frequency": 4609500, "modulation": "NFM", "strength": 69}, {"peaker": 0, "moving_average": 69, "time_stamp": 1596619761, "frequency": 4609625, "modulation": "NFM", "strength": 67}, {"peaker": 0, "moving_average": 69, "time_stamp": 1596619766, "frequency": 4609750, "modulation": "NFM", "strength": 68}, {"peaker": 0, "moving_average": 69, "time_stamp": 1596619771, "frequency": 4609875, "modulation": "NFM", "strength": 66}, {"peaker": 0, "moving_average": 69, "time_stamp": 1596619776, "frequency": 4610000, "modulation": "NFM", "strength": 73}, {"peaker": 0, "moving_average": 69, "time_stamp": 1596619781, "frequency": 4610125, "modulation": "NFM", "strength": 72}, {"peaker": 0, "moving_average": 69, "time_stamp": 1596619787, "frequency": 4610250, "modulation": "NFM", "strength": 70}, {"peaker": 0, "moving_average": 69, "time_stamp": 1596619792, "frequency": 4610375, "modulation": "NFM", "strength": 70}, {"peaker": 0, "moving_average": 69, "time_stamp": 1596619797, "frequency": 4610500, "modulation": "NFM", "strength": 69}, {"peaker": 0, "moving_average": 69, "time_stamp": 1596619802, "frequency": 4610625, "modulation": "NFM", "strength": 69}, {"peaker": 0, "moving_average": 69, "time_stamp": 1596619807, "frequency": 4610750, "modulation": "NFM", "strength": 69}, {"peaker": 0, "moving_average": 69, "time_stamp": 1596619812, "frequency": 4610875, "modulation": "NFM", "strength": 83}, {"peaker": 0, "moving_average": 69, "time_stamp": 1596619817, "frequency": 4611000, "modulation": "NFM", "strength": 69}, {"peaker": 0, "moving_average": 69, "time_stamp": 1596619822, "frequency": 4611125, "modulation": "NFM", "strength": 68}, {"peaker": 0, "moving_average": 69, "time_stamp": 1596619827, "frequency": 4611250, "modulation": "NFM", "strength": 71}, {"peaker": 0, "moving_average": 69, "time_stamp": 1596619832, "frequency": 4611375, "modulation": "NFM", "strength": 78}, {"peaker": 0, "moving_average": 69, "time_stamp": 1596619837, "frequency": 4611500, "modulation": "NFM", "strength": 67}, {"peaker": 0, "moving_average": 69, "time_stamp": 1596619842, "frequency": 4611625, "modulation": "NFM", "strength": 69}, {"peaker": 0, "moving_average": 69, "time_stamp": 1596619847, "frequency": 4611750, "modulation": "NFM", "strength": 67}, {"peaker": 0, "moving_average": 69, "time_stamp": 1596619852, "frequency": 4611875, "modulation": "NFM", "strength": 67}, {"peaker": 0, "moving_average": 69, "time_stamp": 1596619857, "frequency": 4612000, "modulation": "NFM", "strength": 66}, {"peaker": 0, "moving_average": 69, "time_stamp": 1596619862, "frequency": 4612125, "modulation": "NFM", "strength": 66}, {"peaker": 0, "moving_average": 69, "time_stamp": 1596619867, "frequency": 4612250, "modulation": "NFM", "strength": 69}, {"peaker": 0, "moving_average": 69, "time_stamp": 1596619872, "frequency": 4612375, "modulation": "NFM", "strength": 75}, {"peaker": 0, "moving_average": 69, "time_stamp": 1596619877, "frequency": 4612500, "modulation": "NFM", "strength": 70}, {"peaker": 0, "moving_average": 69, "time_stamp": 1596619882, "frequency": 4612625, "modulation": "NFM", "strength": 68}, {"peaker": 0, "moving_average": 69, "time_stamp": 1596619887, "frequency": 4612750, "modulation": "NFM", "strength": 69}, {"peaker": 0, "moving_average": 69, "time_stamp": 1596619892, "frequency": 4612875, "modulation": "NFM", "strength": 78}, {"peaker": 0, "moving_average": 69, "time_stamp": 1596619897, "frequency": 4613000, "modulation": "NFM", "strength": 66}, {"peaker": 0, "moving_average": 69, "time_stamp": 1596619902, "frequency": 4613125, "modulation": "NFM", "strength": 69}, {"peaker": 0, "moving_average": 69, "time_stamp": 1596619907, "frequency": 4613250, "modulation": "NFM", "strength": 58}, {"peaker": 0, "moving_average": 69, "time_stamp": 1596619912, "frequency": 4613375, "modulation": "NFM", "strength": 72}, {"peaker": 0, "moving_average": 69, "time_stamp": 1596619917, "frequency": 4613500, "modulation": "NFM", "strength": 69}, {"peaker": 0, "moving_average": 69, "time_stamp": 1596619922, "frequency": 4613625, "modulation": "NFM", "strength": 72}, {"peaker": 1, "moving_average": 70, "time_stamp": 1596619927, "frequency": 4613750, "modulation": "NFM", "strength": 161}, {"peaker": 0, "moving_average": 70, "time_stamp": 1596619932, "frequency": 4613875, "modulation": "NFM", "strength": 73}, {"peaker": 0, "moving_average": 70, "time_stamp": 1596619937, "frequency": 4614000, "modulation": "NFM", "strength": 71}, {"peaker": 0, "moving_average": 70, "time_stamp": 1596619943, "frequency": 4614125, "modulation": "NFM", "strength": 72}, {"peaker": 0, "moving_average": 70, "time_stamp": 1596619948, "frequency": 4614250, "modulation": "NFM", "strength": 69}, {"peaker": 0, "moving_average": 70, "time_stamp": 1596619953, "frequency": 4614375, "modulation": "NFM", "strength": 69}, {"peaker": 0, "moving_average": 70, "time_stamp": 1596619958, "frequency": 4614500, "modulation": "NFM", "strength": 78}, {"peaker": 0, "moving_average": 70, "time_stamp": 1596619963, "frequency": 4614625, "modulation": "NFM", "strength": 74}, {"peaker": 0, "moving_average": 70, "time_stamp": 1596619968, "frequency": 4614750, "modulation": "NFM", "strength": 64}, {"peaker": 0, "moving_average": 70, "time_stamp": 1596619973, "frequency": 4614875, "modulation": "NFM", "strength": 64}, {"peaker": 0, "moving_average": 70, "time_stamp": 1596619978, "frequency": 4615000, "modulation": "NFM", "strength": 59}, {"peaker": 0, "moving_average": 70, "time_stamp": 1596619983, "frequency": 4615125, "modulation": "NFM", "strength": 70}, {"peaker": 0, "moving_average": 70, "time_stamp": 1596619988, "frequency": 4615250, "modulation": "NFM", "strength": 70}, {"peaker": 0, "moving_average": 70, "time_stamp": 1596619993, "frequency": 4615375, "modulation": "NFM", "strength": 70}, {"peaker": 0, "moving_average": 70, "time_stamp": 1596619998, "frequency": 4615500, "modulation": "NFM", "strength": 57}, {"peaker": 0, "moving_average": 70, "time_stamp": 1596620003, "frequency": 4615625, "modulation": "NFM", "strength": 71}, {"peaker": 0, "moving_average": 70, "time_stamp": 1596620008, "frequency": 4615750, "modulation": "NFM", "strength": 70}, {"peaker": 0, "moving_average": 70, "time_stamp": 1596620013, "frequency": 4615875, "modulation": "NFM", "strength": 70}, {"peaker": 0, "moving_average": 70, "time_stamp": 1596620018, "frequency": 4616000, "modulation": "NFM", "strength": 59}, {"peaker": 0, "moving_average": 70, "time_stamp": 1596620023, "frequency": 4616125, "modulation": "NFM", "strength": 82}, {"peaker": 0, "moving_average": 70, "time_stamp": 1596620028, "frequency": 4616250, "modulation": "NFM", "strength": 59}, {"peaker": 0, "moving_average": 70, "time_stamp": 1596620033, "frequency": 4616375, "modulation": "NFM", "strength": 79}, {"peaker": 0, "moving_average": 70, "time_stamp": 1596620038, "frequency": 4616500, "modulation": "NFM", "strength": 75}, {"peaker": 0, "moving_average": 70, "time_stamp": 1596620043, "frequency": 4616625, "modulation": "NFM", "strength": 70}, {"peaker": 0, "moving_average": 70, "time_stamp": 1596620048, "frequency": 4616750, "modulation": "NFM", "strength": 69}, {"peaker": 0, "moving_average": 70, "time_stamp": 1596620053, "frequency": 4616875, "modulation": "NFM", "strength": 68}, {"peaker": 0, "moving_average": 70, "time_stamp": 1596620058, "frequency": 4617000, "modulation": "NFM", "strength": 69}, {"peaker": 0, "moving_average": 70, "time_stamp": 1596620063, "frequency": 4617125, "modulation": "NFM", "strength": 70}, {"peaker": 0, "moving_average": 70, "time_stamp": 1596620068, "frequency": 4617250, "modulation": "NFM", "strength": 69}, {"peaker": 0, "moving_average": 70, "time_stamp": 1596620073, "frequency": 4617375, "modulation": "NFM", "strength": 70}, {"peaker": 0, "moving_average": 70, "time_stamp": 1596620078, "frequency": 4617500, "modulation": "NFM", "strength": 69}, {"peaker": 0, "moving_average": 70, "time_stamp": 1596620083, "frequency": 4617625, "modulation": "NFM", "strength": 67}, {"peaker": 0, "moving_average": 70, "time_stamp": 1596620088, "frequency": 4617750, "modulation": "NFM", "strength": 69}, {"peaker": 0, "moving_average": 70, "time_stamp": 1596620094, "frequency": 4617875, "modulation": "NFM", "strength": 81}, {"peaker": 0, "moving_average": 70, "time_stamp": 1596620099, "frequency": 4618000, "modulation": "NFM", "strength": 59}, {"peaker": 0, "moving_average": 70, "time_stamp": 1596620104, "frequency": 4618125, "modulation": "NFM", "strength": 70}, {"peaker": 0, "moving_average": 70, "time_stamp": 1596620109, "frequency": 4618250, "modulation": "NFM", "strength": 66}, {"peaker": 1, "moving_average": 71, "time_stamp": 1596620114, "frequency": 4618375, "modulation": "NFM", "strength": 145}, {"peaker": 0, "moving_average": 71, "time_stamp": 1596620119, "frequency": 4618500, "modulation": "NFM", "strength": 68}, {"peaker": 0, "moving_average": 71, "time_stamp": 1596620124, "frequency": 4618625, "modulation": "NFM", "strength": 65}, {"peaker": 0, "moving_average": 71, "time_stamp": 1596620129, "frequency": 4618750, "modulation": "NFM", "strength": 69}, {"peaker": 0, "moving_average": 71, "time_stamp": 1596620134, "frequency": 4618875, "modulation": "NFM", "strength": 80}, {"peaker": 0, "moving_average": 71, "time_stamp": 1596620139, "frequency": 4619000, "modulation": "NFM", "strength": 69}, {"peaker": 0, "moving_average": 71, "time_stamp": 1596620144, "frequency": 4619125, "modulation": "NFM", "strength": 73}, {"peaker": 1, "moving_average": 72, "time_stamp": 1596620149, "frequency": 4619250, "modulation": "NFM", "strength": 119}, {"peaker": 0, "moving_average": 72, "time_stamp": 1596620154, "frequency": 4619375, "modulation": "NFM", "strength": 81}, {"peaker": 0, "moving_average": 72, "time_stamp": 1596620159, "frequency": 4619500, "modulation": "NFM", "strength": 79}, {"peaker": 0, "moving_average": 72, "time_stamp": 1596620164, "frequency": 4619625, "modulation": "NFM", "strength": 80}, {"peaker": 0, "moving_average": 72, "time_stamp": 1596620169, "frequency": 4619750, "modulation": "NFM", "strength": 58}, {"peaker": 0, "moving_average": 72, "time_stamp": 1596620174, "frequency": 4619875, "modulation": "NFM", "strength": 57}, {"peaker": 0, "moving_average": 72, "time_stamp": 1596620179, "frequency": 4620000, "modulation": "NFM", "strength": 72}, {"peaker": 0, "moving_average": 72, "time_stamp": 1596620184, "frequency": 4620125, "modulation": "NFM", "strength": 74}, {"peaker": 0, "moving_average": 72, "time_stamp": 1596620189, "frequency": 4620250, "modulation": "NFM", "strength": 68}, {"peaker": 0, "moving_average": 72, "time_stamp": 1596620194, "frequency": 4620375, "modulation": "NFM", "strength": 70}, {"peaker": 0, "moving_average": 72, "time_stamp": 1596620199, "frequency": 4620500, "modulation": "NFM", "strength": 71}, {"peaker": 0, "moving_average": 72, "time_stamp": 1596620204, "frequency": 4620625, "modulation": "NFM", "strength": 64}, {"peaker": 1, "moving_average": 73, "time_stamp": 1596620209, "frequency": 4620750, "modulation": "NFM", "strength": 162}, {"peaker": 0, "moving_average": 73, "time_stamp": 1596620214, "frequency": 4620875, "modulation": "NFM", "strength": 69}, {"peaker": 0, "moving_average": 73, "time_stamp": 1596620219, "frequency": 4621000, "modulation": "NFM", "strength": 70}, {"peaker": 0, "moving_average": 73, "time_stamp": 1596620224, "frequency": 4621125, "modulation": "NFM", "strength": 74}, {"peaker": 0, "moving_average": 74, "time_stamp": 1596620229, "frequency": 4621250, "modulation": "NFM", "strength": 73}, {"peaker": 0, "moving_average": 74, "time_stamp": 1596620234, "frequency": 4621375, "modulation": "NFM", "strength": 77}, {"peaker": 0, "moving_average": 74, "time_stamp": 1596620239, "frequency": 4621500, "modulation": "NFM", "strength": 73}, {"peaker": 0, "moving_average": 74, "time_stamp": 1596620245, "frequency": 4621625, "modulation": "NFM", "strength": 65}, {"peaker": 0, "moving_average": 74, "time_stamp": 1596620250, "frequency": 4621750, "modulation": "NFM", "strength": 69}, {"peaker": 0, "moving_average": 73, "time_stamp": 1596620255, "frequency": 4621875, "modulation": "NFM", "strength": 67}, {"peaker": 0, "moving_average": 73, "time_stamp": 1596620260, "frequency": 4622000, "modulation": "NFM", "strength": 61}, {"peaker": 0, "moving_average": 73, "time_stamp": 1596620265, "frequency": 4622125, "modulation": "NFM", "strength": 65}, {"peaker": 0, "moving_average": 73, "time_stamp": 1596620270, "frequency": 4622250, "modulation": "NFM", "strength": 69}, {"peaker": 0, "moving_average": 74, "time_stamp": 1596620275, "frequency": 4622375, "modulation": "NFM", "strength": 83}, {"peaker": 0, "moving_average": 74, "time_stamp": 1596620280, "frequency": 4622500, "modulation": "NFM", "strength": 69}, {"peaker": 0, "moving_average": 74, "time_stamp": 1596620285, "frequency": 4622625, "modulation": "NFM", "strength": 76}, {"peaker": 0, "moving_average": 72, "time_stamp": 1596620290, "frequency": 4622750, "modulation": "NFM", "strength": 67}, {"peaker": 0, "moving_average": 72, "time_stamp": 1596620295, "frequency": 4622875, "modulation": "NFM", "strength": 67}, {"peaker": 0, "moving_average": 72, "time_stamp": 1596620300, "frequency": 4623000, "modulation": "NFM", "strength": 67}, {"peaker": 0, "moving_average": 72, "time_stamp": 1596620305, "frequency": 4623125, "modulation": "NFM", "strength": 71}, {"peaker": 0, "moving_average": 72, "time_stamp": 1596620310, "frequency": 4623250, "modulation": "NFM", "strength": 74}, {"peaker": 0, "moving_average": 72, "time_stamp": 1596620315, "frequency": 4623375, "modulation": "NFM", "strength": 70}, {"peaker": 0, "moving_average": 72, "time_stamp": 1596620320, "frequency": 4623500, "modulation": "NFM", "strength": 68}, {"peaker": 0, "moving_average": 72, "time_stamp": 1596620325, "frequency": 4623625, "modulation": "NFM", "strength": 67}, {"peaker": 0, "moving_average": 72, "time_stamp": 1596620330, "frequency": 4623750, "modulation": "NFM", "strength": 68}, {"peaker": 0, "moving_average": 72, "time_stamp": 1596620335, "frequency": 4623875, "modulation": "NFM", "strength": 71}, {"peaker": 0, "moving_average": 72, "time_stamp": 1596620340, "frequency": 4624000, "modulation": "NFM", "strength": 69}, {"peaker": 0, "moving_average": 72, "time_stamp": 1596620345, "frequency": 4624125, "modulation": "NFM", "strength": 71}, {"peaker": 0, "moving_average": 72, "time_stamp": 1596620350, "frequency": 4624250, "modulation": "NFM", "strength": 73}, {"peaker": 0, "moving_average": 72, "time_stamp": 1596620355, "frequency": 4624375, "modulation": "NFM", "strength": 70}, {"peaker": 0, "moving_average": 73, "time_stamp": 1596620360, "frequency": 4624500, "modulation": "NFM", "strength": 74}, {"peaker": 0, "moving_average": 73, "time_stamp": 1596620365, "frequency": 4624625, "modulation": "NFM", "strength": 71}, {"peaker": 0, "moving_average": 73, "time_stamp": 1596620370, "frequency": 4624750, "modulation": "NFM", "strength": 69}, {"peaker": 0, "moving_average": 73, "time_stamp": 1596620375, "frequency": 4624875, "modulation": "NFM", "strength": 75}, {"peaker": 0, "moving_average": 73, "time_stamp": 1596620380, "frequency": 4625000, "modulation": "NFM", "strength": 71}, {"peaker": 0, "moving_average": 73, "time_stamp": 1596620385, "frequency": 4625125, "modulation": "NFM", "strength": 79}, {"peaker": 0, "moving_average": 73, "time_stamp": 1596620391, "frequency": 4625250, "modulation": "NFM", "strength": 70}, {"peaker": 0, "moving_average": 73, "time_stamp": 1596620396, "frequency": 4625375, "modulation": "NFM", "strength": 70}, {"peaker": 0, "moving_average": 73, "time_stamp": 1596620401, "frequency": 4625500, "modulation": "NFM", "strength": 72}, {"peaker": 0, "moving_average": 73, "time_stamp": 1596620406, "frequency": 4625625, "modulation": "NFM", "strength": 73}, {"peaker": 0, "moving_average": 73, "time_stamp": 1596620411, "frequency": 4625750, "modulation": "NFM", "strength": 72}, {"peaker": 0, "moving_average": 73, "time_stamp": 1596620416, "frequency": 4625875, "modulation": "NFM", "strength": 67}, {"peaker": 0, "moving_average": 73, "time_stamp": 1596620421, "frequency": 4626000, "modulation": "NFM", "strength": 79}, {"peaker": 0, "moving_average": 73, "time_stamp": 1596620426, "frequency": 4626125, "modulation": "NFM", "strength": 69}, {"peaker": 0, "moving_average": 73, "time_stamp": 1596620431, "frequency": 4626250, "modulation": "NFM", "strength": 67}, {"peaker": 0, "moving_average": 73, "time_stamp": 1596620436, "frequency": 4626375, "modulation": "NFM", "strength": 69}, {"peaker": 0, "moving_average": 73, "time_stamp": 1596620441, "frequency": 4626500, "modulation": "NFM", "strength": 58}, {"peaker": 0, "moving_average": 73, "time_stamp": 1596620446, "frequency": 4626625, "modulation": "NFM", "strength": 66}, {"peaker": 0, "moving_average": 73, "time_stamp": 1596620451, "frequency": 4626750, "modulation": "NFM", "strength": 73}, {"peaker": 0, "moving_average": 73, "time_stamp": 1596620456, "frequency": 4626875, "modulation": "NFM", "strength": 72}, {"peaker": 0, "moving_average": 73, "time_stamp": 1596620461, "frequency": 4627000, "modulation": "NFM", "strength": 66}, {"peaker": 0, "moving_average": 73, "time_stamp": 1596620466, "frequency": 4627125, "modulation": "NFM", "strength": 70}, {"peaker": 0, "moving_average": 73, "time_stamp": 1596620471, "frequency": 4627250, "modulation": "NFM", "strength": 71}, {"peaker": 0, "moving_average": 72, "time_stamp": 1596620476, "frequency": 4627375, "modulation": "NFM", "strength": 68}, {"peaker": 0, "moving_average": 72, "time_stamp": 1596620481, "frequency": 4627500, "modulation": "NFM", "strength": 70}, {"peaker": 0, "moving_average": 72, "time_stamp": 1596620486, "frequency": 4627625, "modulation": "NFM", "strength": 70}, {"peaker": 0, "moving_average": 72, "time_stamp": 1596620491, "frequency": 4627750, "modulation": "NFM", "strength": 69}, {"peaker": 0, "moving_average": 72, "time_stamp": 1596620496, "frequency": 4627875, "modulation": "NFM", "strength": 68}, {"peaker": 0, "moving_average": 72, "time_stamp": 1596620501, "frequency": 4628000, "modulation": "NFM", "strength": 73}, {"peaker": 0, "moving_average": 72, "time_stamp": 1596620506, "frequency": 4628125, "modulation": "NFM", "strength": 70}, {"peaker": 0, "moving_average": 71, "time_stamp": 1596620511, "frequency": 4628250, "modulation": "NFM", "strength": 74}, {"peaker": 0, "moving_average": 71, "time_stamp": 1596620516, "frequency": 4628375, "modulation": "NFM", "strength": 62}, {"peaker": 0, "moving_average": 71, "time_stamp": 1596620521, "frequency": 4628500, "modulation": "NFM", "strength": 68}, {"peaker": 0, "moving_average": 71, "time_stamp": 1596620526, "frequency": 4628625, "modulation": "NFM", "strength": 71}, {"peaker": 0, "moving_average": 71, "time_stamp": 1596620531, "frequency": 4628750, "modulation": "NFM", "strength": 69}, {"peaker": 0, "moving_average": 71, "time_stamp": 1596620536, "frequency": 4628875, "modulation": "NFM", "strength": 68}, {"peaker": 0, "moving_average": 71, "time_stamp": 1596620541, "frequency": 4629000, "modulation": "NFM", "strength": 69}, {"peaker": 0, "moving_average": 71, "time_stamp": 1596620547, "frequency": 4629125, "modulation": "NFM", "strength": 71}, {"peaker": 0, "moving_average": 71, "time_stamp": 1596620552, "frequency": 4629250, "modulation": "NFM", "strength": 71}, {"peaker": 0, "moving_average": 71, "time_stamp": 1596620557, "frequency": 4629375, "modulation": "NFM", "strength": 71}, {"peaker": 0, "moving_average": 71, "time_stamp": 1596620562, "frequency": 4629500, "modulation": "NFM", "strength": 73}, {"peaker": 0, "moving_average": 71, "time_stamp": 1596620567, "frequency": 4629625, "modulation": "NFM", "strength": 70}, {"peaker": 0, "moving_average": 70, "time_stamp": 1596620572, "frequency": 4629750, "modulation": "NFM", "strength": 62}, {"peaker": 0, "moving_average": 69, "time_stamp": 1596620577, "frequency": 4629875, "modulation": "NFM", "strength": 63}, {"peaker": 0, "moving_average": 70, "time_stamp": 1596620582, "frequency": 4630000, "modulation": "NFM", "strength": 73}, {"peaker": 0, "moving_average": 69, "time_stamp": 1596620587, "frequency": 4630125, "modulation": "NFM", "strength": 70}, {"peaker": 0, "moving_average": 69, "time_stamp": 1596620592, "frequency": 4630250, "modulation": "NFM", "strength": 69}, {"peaker": 0, "moving_average": 69, "time_stamp": 1596620597, "frequency": 4630375, "modulation": "NFM", "strength": 83}, {"peaker": 0, "moving_average": 69, "time_stamp": 1596620602, "frequency": 4630500, "modulation": "NFM", "strength": 70}, {"peaker": 0, "moving_average": 69, "time_stamp": 1596620607, "frequency": 4630625, "modulation": "NFM", "strength": 61}, {"peaker": 0, "moving_average": 69, "time_stamp": 1596620612, "frequency": 4630750, "modulation": "NFM", "strength": 62}, {"peaker": 0, "moving_average": 69, "time_stamp": 1596620617, "frequency": 4630875, "modulation": "NFM", "strength": 63}, {"peaker": 0, "moving_average": 69, "time_stamp": 1596620622, "frequency": 4631000, "modulation": "NFM", "strength": 70}, {"peaker": 0, "moving_average": 69, "time_stamp": 1596620627, "frequency": 4631125, "modulation": "NFM", "strength": 60}, {"peaker": 0, "moving_average": 69, "time_stamp": 1596620632, "frequency": 4631250, "modulation": "NFM", "strength": 61}, {"peaker": 0, "moving_average": 69, "time_stamp": 1596620637, "frequency": 4631375, "modulation": "NFM", "strength": 60}, {"peaker": 0, "moving_average": 69, "time_stamp": 1596620642, "frequency": 4631500, "modulation": "NFM", "strength": 78}, {"peaker": 0, "moving_average": 69, "time_stamp": 1596620647, "frequency": 4631625, "modulation": "NFM", "strength": 67}, {"peaker": 0, "moving_average": 69, "time_stamp": 1596620652, "frequency": 4631750, "modulation": "NFM", "strength": 74}, {"peaker": 0, "moving_average": 69, "time_stamp": 1596620657, "frequency": 4631875, "modulation": "NFM", "strength": 69}, {"peaker": 0, "moving_average": 69, "time_stamp": 1596620662, "frequency": 4632000, "modulation": "NFM", "strength": 70}, {"peaker": 0, "moving_average": 69, "time_stamp": 1596620667, "frequency": 4632125, "modulation": "NFM", "strength": 61}, {"peaker": 0, "moving_average": 69, "time_stamp": 1596620672, "frequency": 4632250, "modulation": "NFM", "strength": 68}, {"peaker": 0, "moving_average": 69, "time_stamp": 1596620677, "frequency": 4632375, "modulation": "NFM", "strength": 70}, {"peaker": 0, "moving_average": 69, "time_stamp": 1596620682, "frequency": 4632500, "modulation": "NFM", "strength": 74}, {"peaker": 0, "moving_average": 69, "time_stamp": 1596620687, "frequency": 4632625, "modulation": "NFM", "strength": 63}, {"peaker": 0, "moving_average": 69, "time_stamp": 1596620693, "frequency": 4632750, "modulation": "NFM", "strength": 70}, {"peaker": 0, "moving_average": 69, "time_stamp": 1596620698, "frequency": 4632875, "modulation": "NFM", "strength": 67}, {"peaker": 0, "moving_average": 69, "time_stamp": 1596620703, "frequency": 4633000, "modulation": "NFM", "strength": 64}, {"peaker": 0, "moving_average": 69, "time_stamp": 1596620708, "frequency": 4633125, "modulation": "NFM", "strength": 71}, {"peaker": 0, "moving_average": 69, "time_stamp": 1596620713, "frequency": 4633250, "modulation": "NFM", "strength": 68}, {"peaker": 0, "moving_average": 69, "time_stamp": 1596620718, "frequency": 4633375, "modulation": "NFM", "strength": 70}, {"peaker": 0, "moving_average": 69, "time_stamp": 1596620723, "frequency": 4633500, "modulation": "NFM", "strength": 69}, {"peaker": 0, "moving_average": 69, "time_stamp": 1596620728, "frequency": 4633625, "modulation": "NFM", "strength": 71}, {"peaker": 0, "moving_average": 69, "time_stamp": 1596620733, "frequency": 4633750, "modulation": "NFM", "strength": 68}, {"peaker": 0, "moving_average": 68, "time_stamp": 1596620738, "frequency": 4633875, "modulation": "NFM", "strength": 67}, {"peaker": 0, "moving_average": 68, "time_stamp": 1596620743, "frequency": 4634000, "modulation": "NFM", "strength": 66}, {"peaker": 0, "moving_average": 68, "time_stamp": 1596620748, "frequency": 4634125, "modulation": "NFM", "strength": 68}, {"peaker": 0, "moving_average": 68, "time_stamp": 1596620753, "frequency": 4634250, "modulation": "NFM", "strength": 64}, {"peaker": 0, "moving_average": 68, "time_stamp": 1596620758, "frequency": 4634375, "modulation": "NFM", "strength": 71}, {"peaker": 0, "moving_average": 68, "time_stamp": 1596620763, "frequency": 4634500, "modulation": "NFM", "strength": 69}, {"peaker": 1, "moving_average": 69, "time_stamp": 1596620768, "frequency": 4634625, "modulation": "NFM", "strength": 146}, {"peaker": 0, "moving_average": 69, "time_stamp": 1596620773, "frequency": 4634750, "modulation": "NFM", "strength": 72}, {"peaker": 0, "moving_average": 69, "time_stamp": 1596620778, "frequency": 4634875, "modulation": "NFM", "strength": 73}, {"peaker": 0, "moving_average": 69, "time_stamp": 1596620783, "frequency": 4635000, "modulation": "NFM", "strength": 60}, {"peaker": 0, "moving_average": 69, "time_stamp": 1596620788, "frequency": 4635125, "modulation": "NFM", "strength": 61}, {"peaker": 0, "moving_average": 69, "time_stamp": 1596620793, "frequency": 4635250, "modulation": "NFM", "strength": 74}, {"peaker": 0, "moving_average": 69, "time_stamp": 1596620798, "frequency": 4635375, "modulation": "NFM", "strength": 72}, {"peaker": 0, "moving_average": 69, "time_stamp": 1596620803, "frequency": 4635500, "modulation": "NFM", "strength": 71}, {"peaker": 0, "moving_average": 69, "time_stamp": 1596620808, "frequency": 4635625, "modulation": "NFM", "strength": 69}, {"peaker": 0, "moving_average": 69, "time_stamp": 1596620813, "frequency": 4635750, "modulation": "NFM", "strength": 69}, {"peaker": 0, "moving_average": 69, "time_stamp": 1596620818, "frequency": 4635875, "modulation": "NFM", "strength": 67}, {"peaker": 0, "moving_average": 69, "time_stamp": 1596620823, "frequency": 4636000, "modulation": "NFM", "strength": 70}, {"peaker": 0, "moving_average": 69, "time_stamp": 1596620828, "frequency": 4636125, "modulation": "NFM", "strength": 69}, {"peaker": 0, "moving_average": 69, "time_stamp": 1596620833, "frequency": 4636250, "modulation": "NFM", "strength": 79}, {"peaker": 0, "moving_average": 69, "time_stamp": 1596620838, "frequency": 4636375, "modulation": "NFM", "strength": 69}, {"peaker": 0, "moving_average": 69, "time_stamp": 1596620844, "frequency": 4636500, "modulation": "NFM", "strength": 68}, {"peaker": 0, "moving_average": 69, "time_stamp": 1596620849, "frequency": 4636625, "modulation": "NFM", "strength": 69}, {"peaker": 0, "moving_average": 69, "time_stamp": 1596620854, "frequency": 4636750, "modulation": "NFM", "strength": 82}, {"peaker": 0, "moving_average": 69, "time_stamp": 1596620859, "frequency": 4636875, "modulation": "NFM", "strength": 69}, {"peaker": 0, "moving_average": 69, "time_stamp": 1596620864, "frequency": 4637000, "modulation": "NFM", "strength": 68}, {"peaker": 0, "moving_average": 69, "time_stamp": 1596620869, "frequency": 4637125, "modulation": "NFM", "strength": 69}, {"peaker": 0, "moving_average": 69, "time_stamp": 1596620874, "frequency": 4637250, "modulation": "NFM", "strength": 68}, {"peaker": 0, "moving_average": 69, "time_stamp": 1596620879, "frequency": 4637375, "modulation": "NFM", "strength": 71}, {"peaker": 0, "moving_average": 69, "time_stamp": 1596620884, "frequency": 4637500, "modulation": "NFM", "strength": 69}, {"peaker": 0, "moving_average": 69, "time_stamp": 1596620889, "frequency": 4637625, "modulation": "NFM", "strength": 73}, {"peaker": 0, "moving_average": 69, "time_stamp": 1596620894, "frequency": 4637750, "modulation": "NFM", "strength": 68}, {"peaker": 0, "moving_average": 69, "time_stamp": 1596620899, "frequency": 4637875, "modulation": "NFM", "strength": 73}, {"peaker": 0, "moving_average": 69, "time_stamp": 1596620904, "frequency": 4638000, "modulation": "NFM", "strength": 70}, {"peaker": 0, "moving_average": 69, "time_stamp": 1596620909, "frequency": 4638125, "modulation": "NFM", "strength": 71}, {"peaker": 1, "moving_average": 71, "time_stamp": 1596620914, "frequency": 4638250, "modulation": "NFM", "strength": 158}, {"peaker": 0, "moving_average": 71, "time_stamp": 1596620919, "frequency": 4638375, "modulation": "NFM", "strength": 75}, {"peaker": 0, "moving_average": 71, "time_stamp": 1596620924, "frequency": 4638500, "modulation": "NFM", "strength": 74}, {"peaker": 0, "moving_average": 71, "time_stamp": 1596620929, "frequency": 4638625, "modulation": "NFM", "strength": 68}, {"peaker": 0, "moving_average": 71, "time_stamp": 1596620934, "frequency": 4638750, "modulation": "NFM", "strength": 72}, {"peaker": 0, "moving_average": 71, "time_stamp": 1596620939, "frequency": 4638875, "modulation": "NFM", "strength": 62}, {"peaker": 0, "moving_average": 71, "time_stamp": 1596620944, "frequency": 4639000, "modulation": "NFM", "strength": 70}, {"peaker": 0, "moving_average": 71, "time_stamp": 1596620949, "frequency": 4639125, "modulation": "NFM", "strength": 75}, {"peaker": 0, "moving_average": 71, "time_stamp": 1596620954, "frequency": 4639250, "modulation": "NFM", "strength": 62}, {"peaker": 0, "moving_average": 71, "time_stamp": 1596620959, "frequency": 4639375, "modulation": "NFM", "strength": 72}, {"peaker": 0, "moving_average": 71, "time_stamp": 1596620964, "frequency": 4639500, "modulation": "NFM", "strength": 71}, {"peaker": 0, "moving_average": 71, "time_stamp": 1596620969, "frequency": 4639625, "modulation": "NFM", "strength": 66}, {"peaker": 0, "moving_average": 71, "time_stamp": 1596620974, "frequency": 4639750, "modulation": "NFM", "strength": 68}, {"peaker": 0, "moving_average": 71, "time_stamp": 1596620979, "frequency": 4639875, "modulation": "NFM", "strength": 63}, {"peaker": 0, "moving_average": 71, "time_stamp": 1596620984, "frequency": 4640000, "modulation": "NFM", "strength": 70}, {"peaker": 0, "moving_average": 71, "time_stamp": 1596620989, "frequency": 4640125, "modulation": "NFM", "strength": 61}, {"peaker": 0, "moving_average": 71, "time_stamp": 1596620995, "frequency": 4640250, "modulation": "NFM", "strength": 69}, {"peaker": 0, "moving_average": 71, "time_stamp": 1596621000, "frequency": 4640375, "modulation": "NFM", "strength": 69}, {"peaker": 0, "moving_average": 71, "time_stamp": 1596621005, "frequency": 4640500, "modulation": "NFM", "strength": 69}, {"peaker": 0, "moving_average": 71, "time_stamp": 1596621010, "frequency": 4640625, "modulation": "NFM", "strength": 64}, {"peaker": 0, "moving_average": 71, "time_stamp": 1596621015, "frequency": 4640750, "modulation": "NFM", "strength": 60}, {"peaker": 0, "moving_average": 71, "time_stamp": 1596621020, "frequency": 4640875, "modulation": "NFM", "strength": 68}, {"peaker": 0, "moving_average": 71, "time_stamp": 1596621025, "frequency": 4641000, "modulation": "NFM", "strength": 69}, {"peaker": 0, "moving_average": 71, "time_stamp": 1596621030, "frequency": 4641125, "modulation": "NFM", "strength": 73}, {"peaker": 0, "moving_average": 71, "time_stamp": 1596621035, "frequency": 4641250, "modulation": "NFM", "strength": 71}, {"peaker": 0, "moving_average": 71, "time_stamp": 1596621040, "frequency": 4641375, "modulation": "NFM", "strength": 69}, {"peaker": 0, "moving_average": 71, "time_stamp": 1596621045, "frequency": 4641500, "modulation": "NFM", "strength": 70}, {"peaker": 0, "moving_average": 71, "time_stamp": 1596621050, "frequency": 4641625, "modulation": "NFM", "strength": 71}, {"peaker": 0, "moving_average": 71, "time_stamp": 1596621055, "frequency": 4641750, "modulation": "NFM", "strength": 63}, {"peaker": 0, "moving_average": 71, "time_stamp": 1596621060, "frequency": 4641875, "modulation": "NFM", "strength": 70}, {"peaker": 0, "moving_average": 71, "time_stamp": 1596621065, "frequency": 4642000, "modulation": "NFM", "strength": 69}, {"peaker": 0, "moving_average": 71, "time_stamp": 1596621070, "frequency": 4642125, "modulation": "NFM", "strength": 67}, {"peaker": 0, "moving_average": 71, "time_stamp": 1596621075, "frequency": 4642250, "modulation": "NFM", "strength": 72}, {"peaker": 0, "moving_average": 71, "time_stamp": 1596621080, "frequency": 4642375, "modulation": "NFM", "strength": 70}, {"peaker": 0, "moving_average": 71, "time_stamp": 1596621085, "frequency": 4642500, "modulation": "NFM", "strength": 62}, {"peaker": 0, "moving_average": 71, "time_stamp": 1596621090, "frequency": 4642625, "modulation": "NFM", "strength": 75}, {"peaker": 0, "moving_average": 71, "time_stamp": 1596621095, "frequency": 4642750, "modulation": "NFM", "strength": 68}, {"peaker": 0, "moving_average": 71, "time_stamp": 1596621100, "frequency": 4642875, "modulation": "NFM", "strength": 69}, {"peaker": 0, "moving_average": 71, "time_stamp": 1596621105, "frequency": 4643000, "modulation": "NFM", "strength": 72}, {"peaker": 0, "moving_average": 71, "time_stamp": 1596621110, "frequency": 4643125, "modulation": "NFM", "strength": 69}, {"peaker": 0, "moving_average": 71, "time_stamp": 1596621115, "frequency": 4643250, "modulation": "NFM", "strength": 78}, {"peaker": 0, "moving_average": 71, "time_stamp": 1596621120, "frequency": 4643375, "modulation": "NFM", "strength": 60}, {"peaker": 0, "moving_average": 71, "time_stamp": 1596621125, "frequency": 4643500, "modulation": "NFM", "strength": 57}, {"peaker": 0, "moving_average": 70, "time_stamp": 1596621130, "frequency": 4643625, "modulation": "NFM", "strength": 71}, {"peaker": 0, "moving_average": 70, "time_stamp": 1596621135, "frequency": 4643750, "modulation": "NFM", "strength": 68}, {"peaker": 0, "moving_average": 70, "time_stamp": 1596621140, "frequency": 4643875, "modulation": "NFM", "strength": 67}, {"peaker": 0, "moving_average": 70, "time_stamp": 1596621146, "frequency": 4644000, "modulation": "NFM", "strength": 77}, {"peaker": 0, "moving_average": 70, "time_stamp": 1596621151, "frequency": 4644125, "modulation": "NFM", "strength": 77}, {"peaker": 0, "moving_average": 70, "time_stamp": 1596621156, "frequency": 4644250, "modulation": "NFM", "strength": 71}, {"peaker": 0, "moving_average": 70, "time_stamp": 1596621161, "frequency": 4644375, "modulation": "NFM", "strength": 71}, {"peaker": 0, "moving_average": 70, "time_stamp": 1596621166, "frequency": 4644500, "modulation": "NFM", "strength": 60}, {"peaker": 0, "moving_average": 70, "time_stamp": 1596621171, "frequency": 4644625, "modulation": "NFM", "strength": 68}, {"peaker": 0, "moving_average": 70, "time_stamp": 1596621176, "frequency": 4644750, "modulation": "NFM", "strength": 67}, {"peaker": 0, "moving_average": 70, "time_stamp": 1596621181, "frequency": 4644875, "modulation": "NFM", "strength": 68}, {"peaker": 0, "moving_average": 70, "time_stamp": 1596621186, "frequency": 4645000, "modulation": "NFM", "strength": 71}, {"peaker": 0, "moving_average": 70, "time_stamp": 1596621191, "frequency": 4645125, "modulation": "NFM", "strength": 61}, {"peaker": 0, "moving_average": 70, "time_stamp": 1596621196, "frequency": 4645250, "modulation": "NFM", "strength": 63}, {"peaker": 0, "moving_average": 70, "time_stamp": 1596621201, "frequency": 4645375, "modulation": "NFM", "strength": 68}, {"peaker": 0, "moving_average": 69, "time_stamp": 1596621206, "frequency": 4645500, "modulation": "NFM", "strength": 57}, {"peaker": 0, "moving_average": 69, "time_stamp": 1596621211, "frequency": 4645625, "modulation": "NFM", "strength": 64}, {"peaker": 0, "moving_average": 69, "time_stamp": 1596621216, "frequency": 4645750, "modulation": "NFM", "strength": 68}, {"peaker": 0, "moving_average": 69, "time_stamp": 1596621221, "frequency": 4645875, "modulation": "NFM", "strength": 69}, {"peaker": 0, "moving_average": 69, "time_stamp": 1596621226, "frequency": 4646000, "modulation": "NFM", "strength": 70}, {"peaker": 0, "moving_average": 69, "time_stamp": 1596621231, "frequency": 4646125, "modulation": "NFM", "strength": 68}, {"peaker": 0, "moving_average": 69, "time_stamp": 1596621236, "frequency": 4646250, "modulation": "NFM", "strength": 81}, {"peaker": 0, "moving_average": 69, "time_stamp": 1596621241, "frequency": 4646375, "modulation": "NFM", "strength": 69}, {"peaker": 1, "moving_average": 70, "time_stamp": 1596621246, "frequency": 4646500, "modulation": "NFM", "strength": 87}, {"peaker": 0, "moving_average": 70, "time_stamp": 1596621251, "frequency": 4646625, "modulation": "NFM", "strength": 67}, {"peaker": 0, "moving_average": 70, "time_stamp": 1596621256, "frequency": 4646750, "modulation": "NFM", "strength": 73}, {"peaker": 0, "moving_average": 70, "time_stamp": 1596621261, "frequency": 4646875, "modulation": "NFM", "strength": 68}, {"peaker": 0, "moving_average": 70, "time_stamp": 1596621266, "frequency": 4647000, "modulation": "NFM", "strength": 76}, {"peaker": 0, "moving_average": 70, "time_stamp": 1596621271, "frequency": 4647125, "modulation": "NFM", "strength": 69}, {"peaker": 0, "moving_average": 68, "time_stamp": 1596621276, "frequency": 4647250, "modulation": "NFM", "strength": 76}, {"peaker": 0, "moving_average": 68, "time_stamp": 1596621281, "frequency": 4647375, "modulation": "NFM", "strength": 68}, {"peaker": 0, "moving_average": 68, "time_stamp": 1596621286, "frequency": 4647500, "modulation": "NFM", "strength": 69}, {"peaker": 0, "moving_average": 68, "time_stamp": 1596621291, "frequency": 4647625, "modulation": "NFM", "strength": 69}, {"peaker": 0, "moving_average": 68, "time_stamp": 1596621297, "frequency": 4647750, "modulation": "NFM", "strength": 69}, {"peaker": 0, "moving_average": 68, "time_stamp": 1596621302, "frequency": 4647875, "modulation": "NFM", "strength": 67}, {"peaker": 0, "moving_average": 68, "time_stamp": 1596621307, "frequency": 4648000, "modulation": "NFM", "strength": 75}, {"peaker": 0, "moving_average": 68, "time_stamp": 1596621312, "frequency": 4648125, "modulation": "NFM", "strength": 69}, {"peaker": 0, "moving_average": 69, "time_stamp": 1596621317, "frequency": 4648250, "modulation": "NFM", "strength": 81}, {"peaker": 0, "moving_average": 69, "time_stamp": 1596621322, "frequency": 4648375, "modulation": "NFM", "strength": 71}, {"peaker": 0, "moving_average": 69, "time_stamp": 1596621327, "frequency": 4648500, "modulation": "NFM", "strength": 71}, {"peaker": 0, "moving_average": 68, "time_stamp": 1596621332, "frequency": 4648625, "modulation": "NFM", "strength": 60}, {"peaker": 0, "moving_average": 68, "time_stamp": 1596621337, "frequency": 4648750, "modulation": "NFM", "strength": 70}, {"peaker": 0, "moving_average": 69, "time_stamp": 1596621342, "frequency": 4648875, "modulation": "NFM", "strength": 75}, {"peaker": 0, "moving_average": 69, "time_stamp": 1596621347, "frequency": 4649000, "modulation": "NFM", "strength": 70}, {"peaker": 0, "moving_average": 69, "time_stamp": 1596621352, "frequency": 4649125, "modulation": "NFM", "strength": 70}, {"peaker": 0, "moving_average": 69, "time_stamp": 1596621357, "frequency": 4649250, "modulation": "NFM", "strength": 65}, {"peaker": 0, "moving_average": 69, "time_stamp": 1596621362, "frequency": 4649375, "modulation": "NFM", "strength": 69}, {"peaker": 0, "moving_average": 69, "time_stamp": 1596621367, "frequency": 4649500, "modulation": "NFM", "strength": 70}, {"peaker": 0, "moving_average": 69, "time_stamp": 1596621372, "frequency": 4649625, "modulation": "NFM", "strength": 59}, {"peaker": 0, "moving_average": 69, "time_stamp": 1596621377, "frequency": 4649750, "modulation": "NFM", "strength": 69}, {"peaker": 0, "moving_average": 69, "time_stamp": 1596621382, "frequency": 4649875, "modulation": "NFM", "strength": 58}, {"peaker": 0, "moving_average": 69, "time_stamp": 1596621387, "frequency": 4650000, "modulation": "NFM", "strength": 69}], "sortie": "b4931324-533d-4278-9fed-2232b14ae374", "version": 1}