{"installation": "ff179504-04ae-45bc-9cf1-b6a5cb111cf7", "band_ndx": 26, "create_time": 1596822719, "observations": [{"peaker": 0, "moving_average": 69, "time_stamp": 1596820705, "frequency": 4600000, "modulation": "NFM", "strength": 69}, {"peaker": 0, "moving_average": 68, "time_stamp": 1596820710, "frequency": 4600125, "modulation": "NFM", "strength": 68}, {"peaker": 0, "moving_average": 70, "time_stamp": 1596820715, "frequency": 4600250, "modulation": "NFM", "strength": 73}, {"peaker": 0, "moving_average": 70, "time_stamp": 1596820721, "frequency": 4600375, "modulation": "NFM", "strength": 70}, {"peaker": 0, "moving_average": 69, "time_stamp": 1596820726, "frequency": 4600500, "modulation": "NFM", "strength": 66}, {"peaker": 0, "moving_average": 69, "time_stamp": 1596820731, "frequency": 4600625, "modulation": "NFM", "strength": 69}, {"peaker": 0, "moving_average": 67, "time_stamp": 1596820736, "frequency": 4600750, "modulation": "NFM", "strength": 59}, {"peaker": 0, "moving_average": 67, "time_stamp": 1596820741, "frequency": 4600875, "modulation": "NFM", "strength": 69}, {"peaker": 0, "moving_average": 68, "time_stamp": 1596820746, "frequency": 4601000, "modulation": "NFM", "strength": 71}, {"peaker": 0, "moving_average": 68, "time_stamp": 1596820751, "frequency": 4601125, "modulation": "NFM", "strength": 68}, {"peaker": 0, "moving_average": 68, "time_stamp": 1596820756, "frequency": 4601250, "modulation": "NFM", "strength": 68}, {"peaker": 0, "moving_average": 68, "time_stamp": 1596820761, "frequency": 4601375, "modulation": "NFM", "strength": 66}, {"peaker": 0, "moving_average": 68, "time_stamp": 1596820766, "frequency": 4601500, "modulation": "NFM", "strength": 75}, {"peaker": 0, "moving_average": 68, "time_stamp": 1596820771, "frequency": 4601625, "modulation": "NFM", "strength": 67}, {"peaker": 0, "moving_average": 68, "time_stamp": 1596820776, "frequency": 4601750, "modulation": "NFM", "strength": 68}, {"peaker": 0, "moving_average": 68, "time_stamp": 1596820781, "frequency": 4601875, "modulation": "NFM", "strength": 68}, {"peaker": 0, "moving_average": 68, "time_stamp": 1596820786, "frequency": 4602000, "modulation": "NFM", "strength": 77}, {"peaker": 0, "moving_average": 68, "time_stamp": 1596820791, "frequency": 4602125, "modulation": "NFM", "strength": 69}, {"peaker": 0, "moving_average": 68, "time_stamp": 1596820796, "frequency": 4602250, "modulation": "NFM", "strength": 58}, {"peaker": 0, "moving_average": 68, "time_stamp": 1596820801, "frequency": 4602375, "modulation": "NFM", "strength": 69}, {"peaker": 0, "moving_average": 68, "time_stamp": 1596820806, "frequency": 4602500, "modulation": "NFM", "strength": 74}, {"peaker": 0, "moving_average": 68, "time_stamp": 1596820811, "frequency": 4602625, "modulation": "NFM", "strength": 63}, {"peaker": 0, "moving_average": 67, "time_stamp": 1596820816, "frequency": 4602750, "modulation": "NFM", "strength": 55}, {"peaker": 0, "moving_average": 67, "time_stamp": 1596820821, "frequency": 4602875, "modulation": "NFM", "strength": 69}, {"peaker": 0, "moving_average": 67, "time_stamp": 1596820826, "frequency": 4603000, "modulation": "NFM", "strength": 68}, {"peaker": 0, "moving_average": 67, "time_stamp": 1596820831, "frequency": 4603125, "modulation": "NFM", "strength": 69}, {"peaker": 0, "moving_average": 67, "time_stamp": 1596820836, "frequency": 4603250, "modulation": "NFM", "strength": 59}, {"peaker": 0, "moving_average": 67, "time_stamp": 1596820841, "frequency": 4603375, "modulation": "NFM", "strength": 68}, {"peaker": 0, "moving_average": 67, "time_stamp": 1596820846, "frequency": 4603500, "modulation": "NFM", "strength": 68}, {"peaker": 0, "moving_average": 67, "time_stamp": 1596820851, "frequency": 4603625, "modulation": "NFM", "strength": 69}, {"peaker": 0, "moving_average": 67, "time_stamp": 1596820856, "frequency": 4603750, "modulation": "NFM", "strength": 69}, {"peaker": 0, "moving_average": 67, "time_stamp": 1596820861, "frequency": 4603875, "modulation": "NFM", "strength": 70}, {"peaker": 0, "moving_average": 67, "time_stamp": 1596820866, "frequency": 4604000, "modulation": "NFM", "strength": 69}, {"peaker": 0, "moving_average": 67, "time_stamp": 1596820872, "frequency": 4604125, "modulation": "NFM", "strength": 58}, {"peaker": 0, "moving_average": 67, "time_stamp": 1596820877, "frequency": 4604250, "modulation": "NFM", "strength": 69}, {"peaker": 0, "moving_average": 67, "time_stamp": 1596820882, "frequency": 4604375, "modulation": "NFM", "strength": 68}, {"peaker": 0, "moving_average": 67, "time_stamp": 1596820887, "frequency": 4604500, "modulation": "NFM", "strength": 62}, {"peaker": 0, "moving_average": 67, "time_stamp": 1596820892, "frequency": 4604625, "modulation": "NFM", "strength": 67}, {"peaker": 0, "moving_average": 67, "time_stamp": 1596820897, "frequency": 4604750, "modulation": "NFM", "strength": 78}, {"peaker": 0, "moving_average": 67, "time_stamp": 1596820902, "frequency": 4604875, "modulation": "NFM", "strength": 67}, {"peaker": 0, "moving_average": 67, "time_stamp": 1596820907, "frequency": 4605000, "modulation": "NFM", "strength": 65}, {"peaker": 0, "moving_average": 67, "time_stamp": 1596820912, "frequency": 4605125, "modulation": "NFM", "strength": 69}, {"peaker": 0, "moving_average": 67, "time_stamp": 1596820917, "frequency": 4605250, "modulation": "NFM", "strength": 68}, {"peaker": 0, "moving_average": 67, "time_stamp": 1596820922, "frequency": 4605375, "modulation": "NFM", "strength": 67}, {"peaker": 0, "moving_average": 67, "time_stamp": 1596820927, "frequency": 4605500, "modulation": "NFM", "strength": 62}, {"peaker": 0, "moving_average": 67, "time_stamp": 1596820932, "frequency": 4605625, "modulation": "NFM", "strength": 57}, {"peaker": 0, "moving_average": 67, "time_stamp": 1596820937, "frequency": 4605750, "modulation": "NFM", "strength": 63}, {"peaker": 0, "moving_average": 67, "time_stamp": 1596820942, "frequency": 4605875, "modulation": "NFM", "strength": 68}, {"peaker": 0, "moving_average": 67, "time_stamp": 1596820947, "frequency": 4606000, "modulation": "NFM", "strength": 61}, {"peaker": 0, "moving_average": 67, "time_stamp": 1596820952, "frequency": 4606125, "modulation": "NFM", "strength": 79}, {"peaker": 0, "moving_average": 67, "time_stamp": 1596820957, "frequency": 4606250, "modulation": "NFM", "strength": 73}, {"peaker": 0, "moving_average": 67, "time_stamp": 1596820962, "frequency": 4606375, "modulation": "NFM", "strength": 77}, {"peaker": 0, "moving_average": 67, "time_stamp": 1596820967, "frequency": 4606500, "modulation": "NFM", "strength": 56}, {"peaker": 0, "moving_average": 67, "time_stamp": 1596820972, "frequency": 4606625, "modulation": "NFM", "strength": 69}, {"peaker": 0, "moving_average": 67, "time_stamp": 1596820977, "frequency": 4606750, "modulation": "NFM", "strength": 68}, {"peaker": 0, "moving_average": 67, "time_stamp": 1596820982, "frequency": 4606875, "modulation": "NFM", "strength": 73}, {"peaker": 0, "moving_average": 67, "time_stamp": 1596820987, "frequency": 4607000, "modulation": "NFM", "strength": 67}, {"peaker": 0, "moving_average": 67, "time_stamp": 1596820992, "frequency": 4607125, "modulation": "NFM", "strength": 70}, {"peaker": 0, "moving_average": 67, "time_stamp": 1596820997, "frequency": 4607250, "modulation": "NFM", "strength": 67}, {"peaker": 0, "moving_average": 67, "time_stamp": 1596821002, "frequency": 4607375, "modulation": "NFM", "strength": 70}, {"peaker": 0, "moving_average": 67, "time_stamp": 1596821007, "frequency": 4607500, "modulation": "NFM", "strength": 68}, {"peaker": 0, "moving_average": 67, "time_stamp": 1596821012, "frequency": 4607625, "modulation": "NFM", "strength": 75}, {"peaker": 0, "moving_average": 67, "time_stamp": 1596821017, "frequency": 4607750, "modulation": "NFM", "strength": 66}, {"peaker": 0, "moving_average": 67, "time_stamp": 1596821023, "frequency": 4607875, "modulation": "NFM", "strength": 81}, {"peaker": 0, "moving_average": 67, "time_stamp": 1596821028, "frequency": 4608000, "modulation": "NFM", "strength": 59}, {"peaker": 0, "moving_average": 67, "time_stamp": 1596821033, "frequency": 4608125, "modulation": "NFM", "strength": 70}, {"peaker": 0, "moving_average": 67, "time_stamp": 1596821038, "frequency": 4608250, "modulation": "NFM", "strength": 61}, {"peaker": 0, "moving_average": 67, "time_stamp": 1596821043, "frequency": 4608375, "modulation": "NFM", "strength": 68}, {"peaker": 0, "moving_average": 67, "time_stamp": 1596821048, "frequency": 4608500, "modulation": "NFM", "strength": 70}, {"peaker": 0, "moving_average": 67, "time_stamp": 1596821053, "frequency": 4608625, "modulation": "NFM", "strength": 56}, {"peaker": 0, "moving_average": 67, "time_stamp": 1596821058, "frequency": 4608750, "modulation": "NFM", "strength": 68}, {"peaker": 0, "moving_average": 67, "time_stamp": 1596821063, "frequency": 4608875, "modulation": "NFM", "strength": 77}, {"peaker": 0, "moving_average": 67, "time_stamp": 1596821068, "frequency": 4609000, "modulation": "NFM", "strength": 68}, {"peaker": 0, "moving_average": 67, "time_stamp": 1596821073, "frequency": 4609125, "modulation": "NFM", "strength": 65}, {"peaker": 0, "moving_average": 67, "time_stamp": 1596821078, "frequency": 4609250, "modulation": "NFM", "strength": 68}, {"peaker": 0, "moving_average": 67, "time_stamp": 1596821083, "frequency": 4609375, "modulation": "NFM", "strength": 68}, {"peaker": 0, "moving_average": 67, "time_stamp": 1596821088, "frequency": 4609500, "modulation": "NFM", "strength": 68}, {"peaker": 0, "moving_average": 67, "time_stamp": 1596821093, "frequency": 4609625, "modulation": "NFM", "strength": 70}, {"peaker": 0, "moving_average": 67, "time_stamp": 1596821098, "frequency": 4609750, "modulation": "NFM", "strength": 70}, {"peaker": 0, "moving_average": 67, "time_stamp": 1596821103, "frequency": 4609875, "modulation": "NFM", "strength": 63}, {"peaker": 0, "moving_average": 67, "time_stamp": 1596821108, "frequency": 4610000, "modulation": "NFM", "strength": 68}, {"peaker": 0, "moving_average": 67, "time_stamp": 1596821113, "frequency": 4610125, "modulation": "NFM", "strength": 69}, {"peaker": 0, "moving_average": 67, "time_stamp": 1596821118, "frequency": 4610250, "modulation": "NFM", "strength": 61}, {"peaker": 0, "moving_average": 67, "time_stamp": 1596821123, "frequency": 4610375, "modulation": "NFM", "strength": 67}, {"peaker": 0, "moving_average": 67, "time_stamp": 1596821128, "frequency": 4610500, "modulation": "NFM", "strength": 68}, {"peaker": 0, "moving_average": 67, "time_stamp": 1596821133, "frequency": 4610625, "modulation": "NFM", "strength": 69}, {"peaker": 0, "moving_average": 67, "time_stamp": 1596821138, "frequency": 4610750, "modulation": "NFM", "strength": 65}, {"peaker": 0, "moving_average": 67, "time_stamp": 1596821143, "frequency": 4610875, "modulation": "NFM", "strength": 64}, {"peaker": 0, "moving_average": 67, "time_stamp": 1596821148, "frequency": 4611000, "modulation": "NFM", "strength": 68}, {"peaker": 0, "moving_average": 67, "time_stamp": 1596821153, "frequency": 4611125, "modulation": "NFM", "strength": 64}, {"peaker": 0, "moving_average": 67, "time_stamp": 1596821158, "frequency": 4611250, "modulation": "NFM", "strength": 80}, {"peaker": 0, "moving_average": 67, "time_stamp": 1596821163, "frequency": 4611375, "modulation": "NFM", "strength": 73}, {"peaker": 0, "moving_average": 67, "time_stamp": 1596821168, "frequency": 4611500, "modulation": "NFM", "strength": 60}, {"peaker": 0, "moving_average": 67, "time_stamp": 1596821173, "frequency": 4611625, "modulation": "NFM", "strength": 66}, {"peaker": 0, "moving_average": 67, "time_stamp": 1596821179, "frequency": 4611750, "modulation": "NFM", "strength": 68}, {"peaker": 0, "moving_average": 67, "time_stamp": 1596821184, "frequency": 4611875, "modulation": "NFM", "strength": 69}, {"peaker": 0, "moving_average": 67, "time_stamp": 1596821189, "frequency": 4612000, "modulation": "NFM", "strength": 67}, {"peaker": 0, "moving_average": 67, "time_stamp": 1596821194, "frequency": 4612125, "modulation": "NFM", "strength": 67}, {"peaker": 0, "moving_average": 67, "time_stamp": 1596821199, "frequency": 4612250, "modulation": "NFM", "strength": 69}, {"peaker": 0, "moving_average": 67, "time_stamp": 1596821204, "frequency": 4612375, "modulation": "NFM", "strength": 71}, {"peaker": 0, "moving_average": 67, "time_stamp": 1596821209, "frequency": 4612500, "modulation": "NFM", "strength": 69}, {"peaker": 0, "moving_average": 67, "time_stamp": 1596821214, "frequency": 4612625, "modulation": "NFM", "strength": 66}, {"peaker": 0, "moving_average": 67, "time_stamp": 1596821219, "frequency": 4612750, "modulation": "NFM", "strength": 68}, {"peaker": 0, "moving_average": 67, "time_stamp": 1596821224, "frequency": 4612875, "modulation": "NFM", "strength": 71}, {"peaker": 0, "moving_average": 67, "time_stamp": 1596821229, "frequency": 4613000, "modulation": "NFM", "strength": 68}, {"peaker": 0, "moving_average": 67, "time_stamp": 1596821234, "frequency": 4613125, "modulation": "NFM", "strength": 68}, {"peaker": 0, "moving_average": 67, "time_stamp": 1596821239, "frequency": 4613250, "modulation": "NFM", "strength": 65}, {"peaker": 0, "moving_average": 67, "time_stamp": 1596821244, "frequency": 4613375, "modulation": "NFM", "strength": 63}, {"peaker": 0, "moving_average": 67, "time_stamp": 1596821249, "frequency": 4613500, "modulation": "NFM", "strength": 65}, {"peaker": 0, "moving_average": 67, "time_stamp": 1596821254, "frequency": 4613625, "modulation": "NFM", "strength": 70}, {"peaker": 1, "moving_average": 69, "time_stamp": 1596821259, "frequency": 4613750, "modulation": "NFM", "strength": 172}, {"peaker": 0, "moving_average": 69, "time_stamp": 1596821264, "frequency": 4613875, "modulation": "NFM", "strength": 69}, {"peaker": 0, "moving_average": 69, "time_stamp": 1596821269, "frequency": 4614000, "modulation": "NFM", "strength": 65}, {"peaker": 0, "moving_average": 69, "time_stamp": 1596821274, "frequency": 4614125, "modulation": "NFM", "strength": 68}, {"peaker": 0, "moving_average": 69, "time_stamp": 1596821279, "frequency": 4614250, "modulation": "NFM", "strength": 69}, {"peaker": 0, "moving_average": 69, "time_stamp": 1596821284, "frequency": 4614375, "modulation": "NFM", "strength": 67}, {"peaker": 0, "moving_average": 69, "time_stamp": 1596821289, "frequency": 4614500, "modulation": "NFM", "strength": 67}, {"peaker": 0, "moving_average": 69, "time_stamp": 1596821294, "frequency": 4614625, "modulation": "NFM", "strength": 68}, {"peaker": 0, "moving_average": 69, "time_stamp": 1596821299, "frequency": 4614750, "modulation": "NFM", "strength": 67}, {"peaker": 0, "moving_average": 69, "time_stamp": 1596821304, "frequency": 4614875, "modulation": "NFM", "strength": 69}, {"peaker": 0, "moving_average": 69, "time_stamp": 1596821309, "frequency": 4615000, "modulation": "NFM", "strength": 68}, {"peaker": 0, "moving_average": 69, "time_stamp": 1596821314, "frequency": 4615125, "modulation": "NFM", "strength": 67}, {"peaker": 0, "moving_average": 69, "time_stamp": 1596821319, "frequency": 4615250, "modulation": "NFM", "strength": 69}, {"peaker": 0, "moving_average": 69, "time_stamp": 1596821325, "frequency": 4615375, "modulation": "NFM", "strength": 69}, {"peaker": 0, "moving_average": 69, "time_stamp": 1596821330, "frequency": 4615500, "modulation": "NFM", "strength": 67}, {"peaker": 0, "moving_average": 69, "time_stamp": 1596821335, "frequency": 4615625, "modulation": "NFM", "strength": 67}, {"peaker": 0, "moving_average": 69, "time_stamp": 1596821340, "frequency": 4615750, "modulation": "NFM", "strength": 67}, {"peaker": 0, "moving_average": 69, "time_stamp": 1596821345, "frequency": 4615875, "modulation": "NFM", "strength": 67}, {"peaker": 0, "moving_average": 69, "time_stamp": 1596821350, "frequency": 4616000, "modulation": "NFM", "strength": 62}, {"peaker": 0, "moving_average": 69, "time_stamp": 1596821355, "frequency": 4616125, "modulation": "NFM", "strength": 69}, {"peaker": 0, "moving_average": 69, "time_stamp": 1596821360, "frequency": 4616250, "modulation": "NFM", "strength": 67}, {"peaker": 0, "moving_average": 69, "time_stamp": 1596821365, "frequency": 4616375, "modulation": "NFM", "strength": 67}, {"peaker": 0, "moving_average": 69, "time_stamp": 1596821370, "frequency": 4616500, "modulation": "NFM", "strength": 68}, {"peaker": 0, "moving_average": 68, "time_stamp": 1596821375, "frequency": 4616625, "modulation": "NFM", "strength": 68}, {"peaker": 0, "moving_average": 68, "time_stamp": 1596821380, "frequency": 4616750, "modulation": "NFM", "strength": 68}, {"peaker": 0, "moving_average": 68, "time_stamp": 1596821385, "frequency": 4616875, "modulation": "NFM", "strength": 78}, {"peaker": 0, "moving_average": 69, "time_stamp": 1596821390, "frequency": 4617000, "modulation": "NFM", "strength": 70}, {"peaker": 0, "moving_average": 69, "time_stamp": 1596821395, "frequency": 4617125, "modulation": "NFM", "strength": 65}, {"peaker": 0, "moving_average": 69, "time_stamp": 1596821400, "frequency": 4617250, "modulation": "NFM", "strength": 68}, {"peaker": 0, "moving_average": 69, "time_stamp": 1596821405, "frequency": 4617375, "modulation": "NFM", "strength": 70}, {"peaker": 0, "moving_average": 69, "time_stamp": 1596821410, "frequency": 4617500, "modulation": "NFM", "strength": 70}, {"peaker": 0, "moving_average": 69, "time_stamp": 1596821415, "frequency": 4617625, "modulation": "NFM", "strength": 70}, {"peaker": 0, "moving_average": 69, "time_stamp": 1596821420, "frequency": 4617750, "modulation": "NFM", "strength": 67}, {"peaker": 0, "moving_average": 69, "time_stamp": 1596821425, "frequency": 4617875, "modulation": "NFM", "strength": 68}, {"peaker": 0, "moving_average": 69, "time_stamp": 1596821430, "frequency": 4618000, "modulation": "NFM", "strength": 74}, {"peaker": 0, "moving_average": 69, "time_stamp": 1596821435, "frequency": 4618125, "modulation": "NFM", "strength": 63}, {"peaker": 0, "moving_average": 69, "time_stamp": 1596821440, "frequency": 4618250, "modulation": "NFM", "strength": 57}, {"peaker": 1, "moving_average": 70, "time_stamp": 1596821445, "frequency": 4618375, "modulation": "NFM", "strength": 151}, {"peaker": 0, "moving_average": 70, "time_stamp": 1596821450, "frequency": 4618500, "modulation": "NFM", "strength": 69}, {"peaker": 0, "moving_average": 70, "time_stamp": 1596821455, "frequency": 4618625, "modulation": "NFM", "strength": 69}, {"peaker": 0, "moving_average": 70, "time_stamp": 1596821460, "frequency": 4618750, "modulation": "NFM", "strength": 69}, {"peaker": 0, "moving_average": 70, "time_stamp": 1596821465, "frequency": 4618875, "modulation": "NFM", "strength": 67}, {"peaker": 0, "moving_average": 70, "time_stamp": 1596821470, "frequency": 4619000, "modulation": "NFM", "strength": 79}, {"peaker": 0, "moving_average": 70, "time_stamp": 1596821476, "frequency": 4619125, "modulation": "NFM", "strength": 71}, {"peaker": 1, "moving_average": 70, "time_stamp": 1596821481, "frequency": 4619250, "modulation": "NFM", "strength": 95}, {"peaker": 0, "moving_average": 70, "time_stamp": 1596821486, "frequency": 4619375, "modulation": "NFM", "strength": 63}, {"peaker": 0, "moving_average": 70, "time_stamp": 1596821491, "frequency": 4619500, "modulation": "NFM", "strength": 68}, {"peaker": 0, "moving_average": 70, "time_stamp": 1596821496, "frequency": 4619625, "modulation": "NFM", "strength": 67}, {"peaker": 0, "moving_average": 70, "time_stamp": 1596821501, "frequency": 4619750, "modulation": "NFM", "strength": 59}, {"peaker": 0, "moving_average": 70, "time_stamp": 1596821506, "frequency": 4619875, "modulation": "NFM", "strength": 64}, {"peaker": 0, "moving_average": 70, "time_stamp": 1596821511, "frequency": 4620000, "modulation": "NFM", "strength": 68}, {"peaker": 0, "moving_average": 70, "time_stamp": 1596821516, "frequency": 4620125, "modulation": "NFM", "strength": 73}, {"peaker": 0, "moving_average": 70, "time_stamp": 1596821521, "frequency": 4620250, "modulation": "NFM", "strength": 74}, {"peaker": 0, "moving_average": 70, "time_stamp": 1596821526, "frequency": 4620375, "modulation": "NFM", "strength": 70}, {"peaker": 0, "moving_average": 70, "time_stamp": 1596821531, "frequency": 4620500, "modulation": "NFM", "strength": 69}, {"peaker": 0, "moving_average": 71, "time_stamp": 1596821536, "frequency": 4620625, "modulation": "NFM", "strength": 73}, {"peaker": 0, "moving_average": 71, "time_stamp": 1596821541, "frequency": 4620750, "modulation": "NFM", "strength": 68}, {"peaker": 0, "moving_average": 71, "time_stamp": 1596821546, "frequency": 4620875, "modulation": "NFM", "strength": 70}, {"peaker": 0, "moving_average": 71, "time_stamp": 1596821551, "frequency": 4621000, "modulation": "NFM", "strength": 68}, {"peaker": 0, "moving_average": 71, "time_stamp": 1596821556, "frequency": 4621125, "modulation": "NFM", "strength": 81}, {"peaker": 0, "moving_average": 71, "time_stamp": 1596821561, "frequency": 4621250, "modulation": "NFM", "strength": 69}, {"peaker": 0, "moving_average": 71, "time_stamp": 1596821566, "frequency": 4621375, "modulation": "NFM", "strength": 69}, {"peaker": 0, "moving_average": 71, "time_stamp": 1596821571, "frequency": 4621500, "modulation": "NFM", "strength": 62}, {"peaker": 0, "moving_average": 71, "time_stamp": 1596821576, "frequency": 4621625, "modulation": "NFM", "strength": 77}, {"peaker": 0, "moving_average": 71, "time_stamp": 1596821581, "frequency": 4621750, "modulation": "NFM", "strength": 67}, {"peaker": 0, "moving_average": 71, "time_stamp": 1596821586, "frequency": 4621875, "modulation": "NFM", "strength": 68}, {"peaker": 0, "moving_average": 71, "time_stamp": 1596821591, "frequency": 4622000, "modulation": "NFM", "strength": 69}, {"peaker": 0, "moving_average": 71, "time_stamp": 1596821596, "frequency": 4622125, "modulation": "NFM", "strength": 68}, {"peaker": 0, "moving_average": 71, "time_stamp": 1596821601, "frequency": 4622250, "modulation": "NFM", "strength": 66}, {"peaker": 0, "moving_average": 71, "time_stamp": 1596821606, "frequency": 4622375, "modulation": "NFM", "strength": 66}, {"peaker": 0, "moving_average": 71, "time_stamp": 1596821611, "frequency": 4622500, "modulation": "NFM", "strength": 61}, {"peaker": 0, "moving_average": 71, "time_stamp": 1596821616, "frequency": 4622625, "modulation": "NFM", "strength": 67}, {"peaker": 0, "moving_average": 69, "time_stamp": 1596821622, "frequency": 4622750, "modulation": "NFM", "strength": 57}, {"peaker": 0, "moving_average": 69, "time_stamp": 1596821627, "frequency": 4622875, "modulation": "NFM", "strength": 67}, {"peaker": 0, "moving_average": 69, "time_stamp": 1596821632, "frequency": 4623000, "modulation": "NFM", "strength": 57}, {"peaker": 0, "moving_average": 69, "time_stamp": 1596821637, "frequency": 4623125, "modulation": "NFM", "strength": 65}, {"peaker": 0, "moving_average": 69, "time_stamp": 1596821642, "frequency": 4623250, "modulation": "NFM", "strength": 63}, {"peaker": 0, "moving_average": 69, "time_stamp": 1596821647, "frequency": 4623375, "modulation": "NFM", "strength": 69}, {"peaker": 0, "moving_average": 69, "time_stamp": 1596821652, "frequency": 4623500, "modulation": "NFM", "strength": 68}, {"peaker": 1, "moving_average": 69, "time_stamp": 1596821657, "frequency": 4623625, "modulation": "NFM", "strength": 94}, {"peaker": 0, "moving_average": 69, "time_stamp": 1596821662, "frequency": 4623750, "modulation": "NFM", "strength": 80}, {"peaker": 0, "moving_average": 69, "time_stamp": 1596821667, "frequency": 4623875, "modulation": "NFM", "strength": 67}, {"peaker": 0, "moving_average": 69, "time_stamp": 1596821672, "frequency": 4624000, "modulation": "NFM", "strength": 67}, {"peaker": 0, "moving_average": 69, "time_stamp": 1596821677, "frequency": 4624125, "modulation": "NFM", "strength": 76}, {"peaker": 0, "moving_average": 69, "time_stamp": 1596821682, "frequency": 4624250, "modulation": "NFM", "strength": 67}, {"peaker": 0, "moving_average": 69, "time_stamp": 1596821687, "frequency": 4624375, "modulation": "NFM", "strength": 69}, {"peaker": 0, "moving_average": 69, "time_stamp": 1596821692, "frequency": 4624500, "modulation": "NFM", "strength": 69}, {"peaker": 0, "moving_average": 69, "time_stamp": 1596821697, "frequency": 4624625, "modulation": "NFM", "strength": 62}, {"peaker": 0, "moving_average": 69, "time_stamp": 1596821702, "frequency": 4624750, "modulation": "NFM", "strength": 68}, {"peaker": 0, "moving_average": 69, "time_stamp": 1596821707, "frequency": 4624875, "modulation": "NFM", "strength": 58}, {"peaker": 0, "moving_average": 69, "time_stamp": 1596821712, "frequency": 4625000, "modulation": "NFM", "strength": 66}, {"peaker": 0, "moving_average": 69, "time_stamp": 1596821717, "frequency": 4625125, "modulation": "NFM", "strength": 61}, {"peaker": 0, "moving_average": 69, "time_stamp": 1596821722, "frequency": 4625250, "modulation": "NFM", "strength": 63}, {"peaker": 0, "moving_average": 69, "time_stamp": 1596821727, "frequency": 4625375, "modulation": "NFM", "strength": 68}, {"peaker": 0, "moving_average": 69, "time_stamp": 1596821732, "frequency": 4625500, "modulation": "NFM", "strength": 58}, {"peaker": 0, "moving_average": 69, "time_stamp": 1596821737, "frequency": 4625625, "modulation": "NFM", "strength": 68}, {"peaker": 0, "moving_average": 69, "time_stamp": 1596821742, "frequency": 4625750, "modulation": "NFM", "strength": 77}, {"peaker": 0, "moving_average": 69, "time_stamp": 1596821747, "frequency": 4625875, "modulation": "NFM", "strength": 69}, {"peaker": 0, "moving_average": 69, "time_stamp": 1596821752, "frequency": 4626000, "modulation": "NFM", "strength": 81}, {"peaker": 0, "moving_average": 69, "time_stamp": 1596821757, "frequency": 4626125, "modulation": "NFM", "strength": 69}, {"peaker": 0, "moving_average": 69, "time_stamp": 1596821762, "frequency": 4626250, "modulation": "NFM", "strength": 71}, {"peaker": 0, "moving_average": 69, "time_stamp": 1596821767, "frequency": 4626375, "modulation": "NFM", "strength": 66}, {"peaker": 0, "moving_average": 69, "time_stamp": 1596821773, "frequency": 4626500, "modulation": "NFM", "strength": 67}, {"peaker": 0, "moving_average": 69, "time_stamp": 1596821778, "frequency": 4626625, "modulation": "NFM", "strength": 74}, {"peaker": 0, "moving_average": 69, "time_stamp": 1596821783, "frequency": 4626750, "modulation": "NFM", "strength": 61}, {"peaker": 0, "moving_average": 69, "time_stamp": 1596821788, "frequency": 4626875, "modulation": "NFM", "strength": 68}, {"peaker": 0, "moving_average": 69, "time_stamp": 1596821793, "frequency": 4627000, "modulation": "NFM", "strength": 71}, {"peaker": 0, "moving_average": 69, "time_stamp": 1596821798, "frequency": 4627125, "modulation": "NFM", "strength": 65}, {"peaker": 0, "moving_average": 69, "time_stamp": 1596821803, "frequency": 4627250, "modulation": "NFM", "strength": 71}, {"peaker": 0, "moving_average": 68, "time_stamp": 1596821808, "frequency": 4627375, "modulation": "NFM", "strength": 68}, {"peaker": 0, "moving_average": 68, "time_stamp": 1596821813, "frequency": 4627500, "modulation": "NFM", "strength": 67}, {"peaker": 0, "moving_average": 68, "time_stamp": 1596821818, "frequency": 4627625, "modulation": "NFM", "strength": 75}, {"peaker": 0, "moving_average": 68, "time_stamp": 1596821823, "frequency": 4627750, "modulation": "NFM", "strength": 72}, {"peaker": 0, "moving_average": 68, "time_stamp": 1596821828, "frequency": 4627875, "modulation": "NFM", "strength": 68}, {"peaker": 0, "moving_average": 68, "time_stamp": 1596821833, "frequency": 4628000, "modulation": "NFM", "strength": 65}, {"peaker": 0, "moving_average": 68, "time_stamp": 1596821838, "frequency": 4628125, "modulation": "NFM", "strength": 69}, {"peaker": 0, "moving_average": 68, "time_stamp": 1596821843, "frequency": 4628250, "modulation": "NFM", "strength": 69}, {"peaker": 0, "moving_average": 68, "time_stamp": 1596821848, "frequency": 4628375, "modulation": "NFM", "strength": 63}, {"peaker": 0, "moving_average": 68, "time_stamp": 1596821853, "frequency": 4628500, "modulation": "NFM", "strength": 60}, {"peaker": 0, "moving_average": 67, "time_stamp": 1596821858, "frequency": 4628625, "modulation": "NFM", "strength": 56}, {"peaker": 0, "moving_average": 68, "time_stamp": 1596821863, "frequency": 4628750, "modulation": "NFM", "strength": 66}, {"peaker": 0, "moving_average": 68, "time_stamp": 1596821868, "frequency": 4628875, "modulation": "NFM", "strength": 68}, {"peaker": 0, "moving_average": 68, "time_stamp": 1596821873, "frequency": 4629000, "modulation": "NFM", "strength": 68}, {"peaker": 0, "moving_average": 68, "time_stamp": 1596821878, "frequency": 4629125, "modulation": "NFM", "strength": 65}, {"peaker": 0, "moving_average": 67, "time_stamp": 1596821883, "frequency": 4629250, "modulation": "NFM", "strength": 70}, {"peaker": 0, "moving_average": 67, "time_stamp": 1596821888, "frequency": 4629375, "modulation": "NFM", "strength": 69}, {"peaker": 0, "moving_average": 67, "time_stamp": 1596821893, "frequency": 4629500, "modulation": "NFM", "strength": 67}, {"peaker": 0, "moving_average": 67, "time_stamp": 1596821898, "frequency": 4629625, "modulation": "NFM", "strength": 61}, {"peaker": 0, "moving_average": 67, "time_stamp": 1596821903, "frequency": 4629750, "modulation": "NFM", "strength": 64}, {"peaker": 0, "moving_average": 67, "time_stamp": 1596821908, "frequency": 4629875, "modulation": "NFM", "strength": 63}, {"peaker": 0, "moving_average": 67, "time_stamp": 1596821913, "frequency": 4630000, "modulation": "NFM", "strength": 67}, {"peaker": 0, "moving_average": 67, "time_stamp": 1596821918, "frequency": 4630125, "modulation": "NFM", "strength": 68}, {"peaker": 0, "moving_average": 67, "time_stamp": 1596821924, "frequency": 4630250, "modulation": "NFM", "strength": 69}, {"peaker": 0, "moving_average": 67, "time_stamp": 1596821929, "frequency": 4630375, "modulation": "NFM", "strength": 64}, {"peaker": 0, "moving_average": 67, "time_stamp": 1596821934, "frequency": 4630500, "modulation": "NFM", "strength": 70}, {"peaker": 0, "moving_average": 67, "time_stamp": 1596821939, "frequency": 4630625, "modulation": "NFM", "strength": 57}, {"peaker": 0, "moving_average": 67, "time_stamp": 1596821944, "frequency": 4630750, "modulation": "NFM", "strength": 73}, {"peaker": 0, "moving_average": 67, "time_stamp": 1596821949, "frequency": 4630875, "modulation": "NFM", "strength": 66}, {"peaker": 0, "moving_average": 67, "time_stamp": 1596821954, "frequency": 4631000, "modulation": "NFM", "strength": 67}, {"peaker": 0, "moving_average": 67, "time_stamp": 1596821959, "frequency": 4631125, "modulation": "NFM", "strength": 68}, {"peaker": 0, "moving_average": 67, "time_stamp": 1596821964, "frequency": 4631250, "modulation": "NFM", "strength": 80}, {"peaker": 0, "moving_average": 67, "time_stamp": 1596821969, "frequency": 4631375, "modulation": "NFM", "strength": 54}, {"peaker": 0, "moving_average": 67, "time_stamp": 1596821974, "frequency": 4631500, "modulation": "NFM", "strength": 68}, {"peaker": 0, "moving_average": 67, "time_stamp": 1596821979, "frequency": 4631625, "modulation": "NFM", "strength": 68}, {"peaker": 0, "moving_average": 67, "time_stamp": 1596821984, "frequency": 4631750, "modulation": "NFM", "strength": 65}, {"peaker": 0, "moving_average": 67, "time_stamp": 1596821989, "frequency": 4631875, "modulation": "NFM", "strength": 62}, {"peaker": 0, "moving_average": 67, "time_stamp": 1596821994, "frequency": 4632000, "modulation": "NFM", "strength": 56}, {"peaker": 0, "moving_average": 67, "time_stamp": 1596821999, "frequency": 4632125, "modulation": "NFM", "strength": 66}, {"peaker": 0, "moving_average": 67, "time_stamp": 1596822004, "frequency": 4632250, "modulation": "NFM", "strength": 74}, {"peaker": 0, "moving_average": 67, "time_stamp": 1596822009, "frequency": 4632375, "modulation": "NFM", "strength": 67}, {"peaker": 0, "moving_average": 67, "time_stamp": 1596822014, "frequency": 4632500, "modulation": "NFM", "strength": 68}, {"peaker": 0, "moving_average": 67, "time_stamp": 1596822019, "frequency": 4632625, "modulation": "NFM", "strength": 66}, {"peaker": 0, "moving_average": 66, "time_stamp": 1596822024, "frequency": 4632750, "modulation": "NFM", "strength": 68}, {"peaker": 0, "moving_average": 66, "time_stamp": 1596822029, "frequency": 4632875, "modulation": "NFM", "strength": 67}, {"peaker": 0, "moving_average": 66, "time_stamp": 1596822034, "frequency": 4633000, "modulation": "NFM", "strength": 66}, {"peaker": 0, "moving_average": 66, "time_stamp": 1596822039, "frequency": 4633125, "modulation": "NFM", "strength": 74}, {"peaker": 0, "moving_average": 66, "time_stamp": 1596822044, "frequency": 4633250, "modulation": "NFM", "strength": 68}, {"peaker": 0, "moving_average": 66, "time_stamp": 1596822049, "frequency": 4633375, "modulation": "NFM", "strength": 69}, {"peaker": 0, "moving_average": 66, "time_stamp": 1596822054, "frequency": 4633500, "modulation": "NFM", "strength": 63}, {"peaker": 0, "moving_average": 66, "time_stamp": 1596822059, "frequency": 4633625, "modulation": "NFM", "strength": 64}, {"peaker": 0, "moving_average": 66, "time_stamp": 1596822064, "frequency": 4633750, "modulation": "NFM", "strength": 67}, {"peaker": 0, "moving_average": 66, "time_stamp": 1596822069, "frequency": 4633875, "modulation": "NFM", "strength": 64}, {"peaker": 0, "moving_average": 67, "time_stamp": 1596822075, "frequency": 4634000, "modulation": "NFM", "strength": 70}, {"peaker": 0, "moving_average": 67, "time_stamp": 1596822080, "frequency": 4634125, "modulation": "NFM", "strength": 74}, {"peaker": 0, "moving_average": 67, "time_stamp": 1596822085, "frequency": 4634250, "modulation": "NFM", "strength": 70}, {"peaker": 0, "moving_average": 67, "time_stamp": 1596822090, "frequency": 4634375, "modulation": "NFM", "strength": 66}, {"peaker": 0, "moving_average": 67, "time_stamp": 1596822095, "frequency": 4634500, "modulation": "NFM", "strength": 78}, {"peaker": 1, "moving_average": 68, "time_stamp": 1596822100, "frequency": 4634625, "modulation": "NFM", "strength": 123}, {"peaker": 0, "moving_average": 68, "time_stamp": 1596822105, "frequency": 4634750, "modulation": "NFM", "strength": 71}, {"peaker": 0, "moving_average": 68, "time_stamp": 1596822110, "frequency": 4634875, "modulation": "NFM", "strength": 72}, {"peaker": 0, "moving_average": 67, "time_stamp": 1596822115, "frequency": 4635000, "modulation": "NFM", "strength": 58}, {"peaker": 0, "moving_average": 67, "time_stamp": 1596822120, "frequency": 4635125, "modulation": "NFM", "strength": 68}, {"peaker": 0, "moving_average": 67, "time_stamp": 1596822125, "frequency": 4635250, "modulation": "NFM", "strength": 68}, {"peaker": 0, "moving_average": 67, "time_stamp": 1596822130, "frequency": 4635375, "modulation": "NFM", "strength": 70}, {"peaker": 0, "moving_average": 67, "time_stamp": 1596822135, "frequency": 4635500, "modulation": "NFM", "strength": 68}, {"peaker": 0, "moving_average": 67, "time_stamp": 1596822140, "frequency": 4635625, "modulation": "NFM", "strength": 77}, {"peaker": 0, "moving_average": 68, "time_stamp": 1596822145, "frequency": 4635750, "modulation": "NFM", "strength": 70}, {"peaker": 0, "moving_average": 68, "time_stamp": 1596822150, "frequency": 4635875, "modulation": "NFM", "strength": 67}, {"peaker": 0, "moving_average": 68, "time_stamp": 1596822155, "frequency": 4636000, "modulation": "NFM", "strength": 69}, {"peaker": 0, "moving_average": 68, "time_stamp": 1596822160, "frequency": 4636125, "modulation": "NFM", "strength": 68}, {"peaker": 0, "moving_average": 68, "time_stamp": 1596822165, "frequency": 4636250, "modulation": "NFM", "strength": 70}, {"peaker": 0, "moving_average": 68, "time_stamp": 1596822170, "frequency": 4636375, "modulation": "NFM", "strength": 68}, {"peaker": 0, "moving_average": 68, "time_stamp": 1596822175, "frequency": 4636500, "modulation": "NFM", "strength": 67}, {"peaker": 0, "moving_average": 67, "time_stamp": 1596822180, "frequency": 4636625, "modulation": "NFM", "strength": 67}, {"peaker": 0, "moving_average": 67, "time_stamp": 1596822185, "frequency": 4636750, "modulation": "NFM", "strength": 66}, {"peaker": 0, "moving_average": 67, "time_stamp": 1596822190, "frequency": 4636875, "modulation": "NFM", "strength": 68}, {"peaker": 0, "moving_average": 67, "time_stamp": 1596822195, "frequency": 4637000, "modulation": "NFM", "strength": 65}, {"peaker": 0, "moving_average": 67, "time_stamp": 1596822200, "frequency": 4637125, "modulation": "NFM", "strength": 65}, {"peaker": 0, "moving_average": 67, "time_stamp": 1596822205, "frequency": 4637250, "modulation": "NFM", "strength": 65}, {"peaker": 0, "moving_average": 67, "time_stamp": 1596822210, "frequency": 4637375, "modulation": "NFM", "strength": 62}, {"peaker": 0, "moving_average": 67, "time_stamp": 1596822215, "frequency": 4637500, "modulation": "NFM", "strength": 68}, {"peaker": 0, "moving_average": 68, "time_stamp": 1596822220, "frequency": 4637625, "modulation": "NFM", "strength": 67}, {"peaker": 0, "moving_average": 68, "time_stamp": 1596822226, "frequency": 4637750, "modulation": "NFM", "strength": 67}, {"peaker": 0, "moving_average": 68, "time_stamp": 1596822231, "frequency": 4637875, "modulation": "NFM", "strength": 69}, {"peaker": 0, "moving_average": 68, "time_stamp": 1596822236, "frequency": 4638000, "modulation": "NFM", "strength": 70}, {"peaker": 0, "moving_average": 68, "time_stamp": 1596822241, "frequency": 4638125, "modulation": "NFM", "strength": 65}, {"peaker": 1, "moving_average": 68, "time_stamp": 1596822246, "frequency": 4638250, "modulation": "NFM", "strength": 128}, {"peaker": 0, "moving_average": 68, "time_stamp": 1596822251, "frequency": 4638375, "modulation": "NFM", "strength": 71}, {"peaker": 0, "moving_average": 68, "time_stamp": 1596822256, "frequency": 4638500, "modulation": "NFM", "strength": 70}, {"peaker": 0, "moving_average": 68, "time_stamp": 1596822261, "frequency": 4638625, "modulation": "NFM", "strength": 59}, {"peaker": 0, "moving_average": 68, "time_stamp": 1596822266, "frequency": 4638750, "modulation": "NFM", "strength": 67}, {"peaker": 0, "moving_average": 69, "time_stamp": 1596822271, "frequency": 4638875, "modulation": "NFM", "strength": 67}, {"peaker": 0, "moving_average": 69, "time_stamp": 1596822276, "frequency": 4639000, "modulation": "NFM", "strength": 67}, {"peaker": 0, "moving_average": 69, "time_stamp": 1596822281, "frequency": 4639125, "modulation": "NFM", "strength": 70}, {"peaker": 0, "moving_average": 69, "time_stamp": 1596822286, "frequency": 4639250, "modulation": "NFM", "strength": 80}, {"peaker": 0, "moving_average": 69, "time_stamp": 1596822291, "frequency": 4639375, "modulation": "NFM", "strength": 72}, {"peaker": 0, "moving_average": 69, "time_stamp": 1596822296, "frequency": 4639500, "modulation": "NFM", "strength": 71}, {"peaker": 0, "moving_average": 69, "time_stamp": 1596822301, "frequency": 4639625, "modulation": "NFM", "strength": 56}, {"peaker": 0, "moving_average": 69, "time_stamp": 1596822306, "frequency": 4639750, "modulation": "NFM", "strength": 66}, {"peaker": 0, "moving_average": 69, "time_stamp": 1596822311, "frequency": 4639875, "modulation": "NFM", "strength": 68}, {"peaker": 0, "moving_average": 69, "time_stamp": 1596822316, "frequency": 4640000, "modulation": "NFM", "strength": 75}, {"peaker": 0, "moving_average": 69, "time_stamp": 1596822321, "frequency": 4640125, "modulation": "NFM", "strength": 65}, {"peaker": 0, "moving_average": 69, "time_stamp": 1596822326, "frequency": 4640250, "modulation": "NFM", "strength": 71}, {"peaker": 0, "moving_average": 69, "time_stamp": 1596822331, "frequency": 4640375, "modulation": "NFM", "strength": 68}, {"peaker": 0, "moving_average": 69, "time_stamp": 1596822336, "frequency": 4640500, "modulation": "NFM", "strength": 67}, {"peaker": 0, "moving_average": 69, "time_stamp": 1596822341, "frequency": 4640625, "modulation": "NFM", "strength": 68}, {"peaker": 0, "moving_average": 69, "time_stamp": 1596822346, "frequency": 4640750, "modulation": "NFM", "strength": 72}, {"peaker": 0, "moving_average": 69, "time_stamp": 1596822351, "frequency": 4640875, "modulation": "NFM", "strength": 66}, {"peaker": 0, "moving_average": 69, "time_stamp": 1596822356, "frequency": 4641000, "modulation": "NFM", "strength": 68}, {"peaker": 0, "moving_average": 69, "time_stamp": 1596822361, "frequency": 4641125, "modulation": "NFM", "strength": 69}, {"peaker": 0, "moving_average": 69, "time_stamp": 1596822366, "frequency": 4641250, "modulation": "NFM", "strength": 69}, {"peaker": 0, "moving_average": 69, "time_stamp": 1596822372, "frequency": 4641375, "modulation": "NFM", "strength": 67}, {"peaker": 0, "moving_average": 69, "time_stamp": 1596822377, "frequency": 4641500, "modulation": "NFM", "strength": 62}, {"peaker": 0, "moving_average": 69, "time_stamp": 1596822382, "frequency": 4641625, "modulation": "NFM", "strength": 67}, {"peaker": 0, "moving_average": 69, "time_stamp": 1596822387, "frequency": 4641750, "modulation": "NFM", "strength": 66}, {"peaker": 0, "moving_average": 69, "time_stamp": 1596822392, "frequency": 4641875, "modulation": "NFM", "strength": 74}, {"peaker": 0, "moving_average": 69, "time_stamp": 1596822397, "frequency": 4642000, "modulation": "NFM", "strength": 67}, {"peaker": 0, "moving_average": 69, "time_stamp": 1596822402, "frequency": 4642125, "modulation": "NFM", "strength": 78}, {"peaker": 0, "moving_average": 69, "time_stamp": 1596822407, "frequency": 4642250, "modulation": "NFM", "strength": 80}, {"peaker": 0, "moving_average": 69, "time_stamp": 1596822412, "frequency": 4642375, "modulation": "NFM", "strength": 72}, {"peaker": 0, "moving_average": 70, "time_stamp": 1596822417, "frequency": 4642500, "modulation": "NFM", "strength": 68}, {"peaker": 0, "moving_average": 69, "time_stamp": 1596822422, "frequency": 4642625, "modulation": "NFM", "strength": 61}, {"peaker": 0, "moving_average": 69, "time_stamp": 1596822427, "frequency": 4642750, "modulation": "NFM", "strength": 64}, {"peaker": 0, "moving_average": 69, "time_stamp": 1596822432, "frequency": 4642875, "modulation": "NFM", "strength": 62}, {"peaker": 0, "moving_average": 69, "time_stamp": 1596822437, "frequency": 4643000, "modulation": "NFM", "strength": 65}, {"peaker": 0, "moving_average": 69, "time_stamp": 1596822442, "frequency": 4643125, "modulation": "NFM", "strength": 68}, {"peaker": 0, "moving_average": 69, "time_stamp": 1596822447, "frequency": 4643250, "modulation": "NFM", "strength": 61}, {"peaker": 0, "moving_average": 69, "time_stamp": 1596822452, "frequency": 4643375, "modulation": "NFM", "strength": 74}, {"peaker": 0, "moving_average": 69, "time_stamp": 1596822457, "frequency": 4643500, "modulation": "NFM", "strength": 61}, {"peaker": 0, "moving_average": 68, "time_stamp": 1596822462, "frequency": 4643625, "modulation": "NFM", "strength": 67}, {"peaker": 0, "moving_average": 68, "time_stamp": 1596822467, "frequency": 4643750, "modulation": "NFM", "strength": 64}, {"peaker": 0, "moving_average": 68, "time_stamp": 1596822472, "frequency": 4643875, "modulation": "NFM", "strength": 71}, {"peaker": 0, "moving_average": 68, "time_stamp": 1596822477, "frequency": 4644000, "modulation": "NFM", "strength": 76}, {"peaker": 0, "moving_average": 68, "time_stamp": 1596822482, "frequency": 4644125, "modulation": "NFM", "strength": 59}, {"peaker": 0, "moving_average": 68, "time_stamp": 1596822487, "frequency": 4644250, "modulation": "NFM", "strength": 81}, {"peaker": 0, "moving_average": 68, "time_stamp": 1596822492, "frequency": 4644375, "modulation": "NFM", "strength": 70}, {"peaker": 0, "moving_average": 68, "time_stamp": 1596822497, "frequency": 4644500, "modulation": "NFM", "strength": 59}, {"peaker": 0, "moving_average": 68, "time_stamp": 1596822502, "frequency": 4644625, "modulation": "NFM", "strength": 65}, {"peaker": 0, "moving_average": 68, "time_stamp": 1596822507, "frequency": 4644750, "modulation": "NFM", "strength": 68}, {"peaker": 0, "moving_average": 68, "time_stamp": 1596822512, "frequency": 4644875, "modulation": "NFM", "strength": 66}, {"peaker": 0, "moving_average": 68, "time_stamp": 1596822517, "frequency": 4645000, "modulation": "NFM", "strength": 67}, {"peaker": 0, "moving_average": 68, "time_stamp": 1596822522, "frequency": 4645125, "modulation": "NFM", "strength": 79}, {"peaker": 0, "moving_average": 68, "time_stamp": 1596822528, "frequency": 4645250, "modulation": "NFM", "strength": 71}, {"peaker": 0, "moving_average": 68, "time_stamp": 1596822533, "frequency": 4645375, "modulation": "NFM", "strength": 74}, {"peaker": 0, "moving_average": 68, "time_stamp": 1596822538, "frequency": 4645500, "modulation": "NFM", "strength": 60}, {"peaker": 0, "moving_average": 68, "time_stamp": 1596822543, "frequency": 4645625, "modulation": "NFM", "strength": 68}, {"peaker": 0, "moving_average": 68, "time_stamp": 1596822548, "frequency": 4645750, "modulation": "NFM", "strength": 68}, {"peaker": 0, "moving_average": 68, "time_stamp": 1596822553, "frequency": 4645875, "modulation": "NFM", "strength": 67}, {"peaker": 0, "moving_average": 68, "time_stamp": 1596822558, "frequency": 4646000, "modulation": "NFM", "strength": 80}, {"peaker": 0, "moving_average": 68, "time_stamp": 1596822563, "frequency": 4646125, "modulation": "NFM", "strength": 67}, {"peaker": 0, "moving_average": 68, "time_stamp": 1596822568, "frequency": 4646250, "modulation": "NFM", "strength": 60}, {"peaker": 0, "moving_average": 69, "time_stamp": 1596822573, "frequency": 4646375, "modulation": "NFM", "strength": 70}, {"peaker": 0, "moving_average": 68, "time_stamp": 1596822578, "frequency": 4646500, "modulation": "NFM", "strength": 63}, {"peaker": 0, "moving_average": 68, "time_stamp": 1596822583, "frequency": 4646625, "modulation": "NFM", "strength": 63}, {"peaker": 0, "moving_average": 69, "time_stamp": 1596822588, "frequency": 4646750, "modulation": "NFM", "strength": 76}, {"peaker": 0, "moving_average": 68, "time_stamp": 1596822593, "frequency": 4646875, "modulation": "NFM", "strength": 66}, {"peaker": 0, "moving_average": 68, "time_stamp": 1596822598, "frequency": 4647000, "modulation": "NFM", "strength": 63}, {"peaker": 0, "moving_average": 68, "time_stamp": 1596822603, "frequency": 4647125, "modulation": "NFM", "strength": 66}, {"peaker": 0, "moving_average": 68, "time_stamp": 1596822608, "frequency": 4647250, "modulation": "NFM", "strength": 68}, {"peaker": 0, "moving_average": 68, "time_stamp": 1596822613, "frequency": 4647375, "modulation": "NFM", "strength": 67}, {"peaker": 0, "moving_average": 67, "time_stamp": 1596822618, "frequency": 4647500, "modulation": "NFM", "strength": 67}, {"peaker": 0, "moving_average": 68, "time_stamp": 1596822623, "frequency": 4647625, "modulation": "NFM", "strength": 68}, {"peaker": 0, "moving_average": 68, "time_stamp": 1596822628, "frequency": 4647750, "modulation": "NFM", "strength": 67}, {"peaker": 0, "moving_average": 68, "time_stamp": 1596822633, "frequency": 4647875, "modulation": "NFM", "strength": 67}, {"peaker": 0, "moving_average": 68, "time_stamp": 1596822638, "frequency": 4648000, "modulation": "NFM", "strength": 69}, {"peaker": 0, "moving_average": 68, "time_stamp": 1596822643, "frequency": 4648125, "modulation": "NFM", "strength": 69}, {"peaker": 0, "moving_average": 67, "time_stamp": 1596822648, "frequency": 4648250, "modulation": "NFM", "strength": 69}, {"peaker": 0, "moving_average": 67, "time_stamp": 1596822653, "frequency": 4648375, "modulation": "NFM", "strength": 67}, {"peaker": 0, "moving_average": 67, "time_stamp": 1596822658, "frequency": 4648500, "modulation": "NFM", "strength": 72}, {"peaker": 0, "moving_average": 68, "time_stamp": 1596822663, "frequency": 4648625, "modulation": "NFM", "strength": 63}, {"peaker": 0, "moving_average": 68, "time_stamp": 1596822668, "frequency": 4648750, "modulation": "NFM", "strength": 67}, {"peaker": 0, "moving_average": 68, "time_stamp": 1596822673, "frequency": 4648875, "modulation": "NFM", "strength": 68}, {"peaker": 0, "moving_average": 67, "time_stamp": 1596822679, "frequency": 4649000, "modulation": "NFM", "strength": 66}, {"peaker": 0, "moving_average": 67, "time_stamp": 1596822684, "frequency": 4649125, "modulation": "NFM", "strength": 68}, {"peaker": 0, "moving_average": 67, "time_stamp": 1596822689, "frequency": 4649250, "modulation": "NFM", "strength": 68}, {"peaker": 0, "moving_average": 67, "time_stamp": 1596822694, "frequency": 4649375, "modulation": "NFM", "strength": 71}, {"peaker": 0, "moving_average": 67, "time_stamp": 1596822699, "frequency": 4649500, "modulation": "NFM", "strength": 67}, {"peaker": 0, "moving_average": 67, "time_stamp": 1596822704, "frequency": 4649625, "modulation": "NFM", "strength": 66}, {"peaker": 0, "moving_average": 67, "time_stamp": 1596822709, "frequency": 4649750, "modulation": "NFM", "strength": 70}, {"peaker": 0, "moving_average": 67, "time_stamp": 1596822714, "frequency": 4649875, "modulation": "NFM", "strength": 71}, {"peaker": 0, "moving_average": 67, "time_stamp": 1596822719, "frequency": 4650000, "modulation": "NFM", "strength": 67}], "sortie": "8eb73ec1-8708-4016-8874-047450ea6cec", "version": 1}