{"installation": "ff179504-04ae-45bc-9cf1-b6a5cb111cf7", "band_ndx": 24, "create_time": 1596818654, "observations": [{"peaker": 0, "moving_average": 101, "time_stamp": 1596816640, "frequency": 4500000, "modulation": "NFM", "strength": 101}, {"peaker": 0, "moving_average": 87, "time_stamp": 1596816645, "frequency": 4500125, "modulation": "NFM", "strength": 73}, {"peaker": 0, "moving_average": 79, "time_stamp": 1596816651, "frequency": 4500250, "modulation": "NFM", "strength": 63}, {"peaker": 0, "moving_average": 77, "time_stamp": 1596816656, "frequency": 4500375, "modulation": "NFM", "strength": 72}, {"peaker": 0, "moving_average": 76, "time_stamp": 1596816661, "frequency": 4500500, "modulation": "NFM", "strength": 72}, {"peaker": 0, "moving_average": 75, "time_stamp": 1596816666, "frequency": 4500625, "modulation": "NFM", "strength": 72}, {"peaker": 0, "moving_average": 74, "time_stamp": 1596816671, "frequency": 4500750, "modulation": "NFM", "strength": 71}, {"peaker": 0, "moving_average": 74, "time_stamp": 1596816676, "frequency": 4500875, "modulation": "NFM", "strength": 72}, {"peaker": 0, "moving_average": 74, "time_stamp": 1596816681, "frequency": 4501000, "modulation": "NFM", "strength": 71}, {"peaker": 0, "moving_average": 73, "time_stamp": 1596816686, "frequency": 4501125, "modulation": "NFM", "strength": 65}, {"peaker": 0, "moving_average": 72, "time_stamp": 1596816691, "frequency": 4501250, "modulation": "NFM", "strength": 70}, {"peaker": 0, "moving_average": 72, "time_stamp": 1596816696, "frequency": 4501375, "modulation": "NFM", "strength": 70}, {"peaker": 0, "moving_average": 72, "time_stamp": 1596816701, "frequency": 4501500, "modulation": "NFM", "strength": 70}, {"peaker": 0, "moving_average": 72, "time_stamp": 1596816706, "frequency": 4501625, "modulation": "NFM", "strength": 67}, {"peaker": 0, "moving_average": 71, "time_stamp": 1596816711, "frequency": 4501750, "modulation": "NFM", "strength": 60}, {"peaker": 0, "moving_average": 71, "time_stamp": 1596816716, "frequency": 4501875, "modulation": "NFM", "strength": 70}, {"peaker": 0, "moving_average": 71, "time_stamp": 1596816721, "frequency": 4502000, "modulation": "NFM", "strength": 69}, {"peaker": 0, "moving_average": 71, "time_stamp": 1596816726, "frequency": 4502125, "modulation": "NFM", "strength": 74}, {"peaker": 0, "moving_average": 70, "time_stamp": 1596816731, "frequency": 4502250, "modulation": "NFM", "strength": 63}, {"peaker": 0, "moving_average": 70, "time_stamp": 1596816736, "frequency": 4502375, "modulation": "NFM", "strength": 73}, {"peaker": 0, "moving_average": 71, "time_stamp": 1596816741, "frequency": 4502500, "modulation": "NFM", "strength": 74}, {"peaker": 0, "moving_average": 71, "time_stamp": 1596816746, "frequency": 4502625, "modulation": "NFM", "strength": 71}, {"peaker": 0, "moving_average": 71, "time_stamp": 1596816751, "frequency": 4502750, "modulation": "NFM", "strength": 70}, {"peaker": 0, "moving_average": 70, "time_stamp": 1596816756, "frequency": 4502875, "modulation": "NFM", "strength": 69}, {"peaker": 0, "moving_average": 70, "time_stamp": 1596816761, "frequency": 4503000, "modulation": "NFM", "strength": 70}, {"peaker": 0, "moving_average": 70, "time_stamp": 1596816766, "frequency": 4503125, "modulation": "NFM", "strength": 73}, {"peaker": 0, "moving_average": 71, "time_stamp": 1596816771, "frequency": 4503250, "modulation": "NFM", "strength": 72}, {"peaker": 0, "moving_average": 71, "time_stamp": 1596816776, "frequency": 4503375, "modulation": "NFM", "strength": 74}, {"peaker": 0, "moving_average": 71, "time_stamp": 1596816781, "frequency": 4503500, "modulation": "NFM", "strength": 76}, {"peaker": 0, "moving_average": 71, "time_stamp": 1596816786, "frequency": 4503625, "modulation": "NFM", "strength": 66}, {"peaker": 0, "moving_average": 71, "time_stamp": 1596816791, "frequency": 4503750, "modulation": "NFM", "strength": 71}, {"peaker": 0, "moving_average": 71, "time_stamp": 1596816796, "frequency": 4503875, "modulation": "NFM", "strength": 71}, {"peaker": 0, "moving_average": 71, "time_stamp": 1596816802, "frequency": 4504000, "modulation": "NFM", "strength": 72}, {"peaker": 0, "moving_average": 71, "time_stamp": 1596816807, "frequency": 4504125, "modulation": "NFM", "strength": 72}, {"peaker": 0, "moving_average": 71, "time_stamp": 1596816812, "frequency": 4504250, "modulation": "NFM", "strength": 74}, {"peaker": 0, "moving_average": 71, "time_stamp": 1596816817, "frequency": 4504375, "modulation": "NFM", "strength": 73}, {"peaker": 0, "moving_average": 71, "time_stamp": 1596816822, "frequency": 4504500, "modulation": "NFM", "strength": 71}, {"peaker": 0, "moving_average": 71, "time_stamp": 1596816827, "frequency": 4504625, "modulation": "NFM", "strength": 71}, {"peaker": 0, "moving_average": 71, "time_stamp": 1596816832, "frequency": 4504750, "modulation": "NFM", "strength": 69}, {"peaker": 0, "moving_average": 70, "time_stamp": 1596816837, "frequency": 4504875, "modulation": "NFM", "strength": 61}, {"peaker": 0, "moving_average": 70, "time_stamp": 1596816842, "frequency": 4505000, "modulation": "NFM", "strength": 72}, {"peaker": 0, "moving_average": 70, "time_stamp": 1596816847, "frequency": 4505125, "modulation": "NFM", "strength": 71}, {"peaker": 0, "moving_average": 71, "time_stamp": 1596816852, "frequency": 4505250, "modulation": "NFM", "strength": 72}, {"peaker": 0, "moving_average": 71, "time_stamp": 1596816857, "frequency": 4505375, "modulation": "NFM", "strength": 71}, {"peaker": 0, "moving_average": 70, "time_stamp": 1596816862, "frequency": 4505500, "modulation": "NFM", "strength": 70}, {"peaker": 0, "moving_average": 70, "time_stamp": 1596816867, "frequency": 4505625, "modulation": "NFM", "strength": 63}, {"peaker": 0, "moving_average": 70, "time_stamp": 1596816872, "frequency": 4505750, "modulation": "NFM", "strength": 73}, {"peaker": 0, "moving_average": 70, "time_stamp": 1596816877, "frequency": 4505875, "modulation": "NFM", "strength": 71}, {"peaker": 0, "moving_average": 70, "time_stamp": 1596816882, "frequency": 4506000, "modulation": "NFM", "strength": 69}, {"peaker": 0, "moving_average": 70, "time_stamp": 1596816887, "frequency": 4506125, "modulation": "NFM", "strength": 72}, {"peaker": 0, "moving_average": 70, "time_stamp": 1596816892, "frequency": 4506250, "modulation": "NFM", "strength": 70}, {"peaker": 0, "moving_average": 70, "time_stamp": 1596816897, "frequency": 4506375, "modulation": "NFM", "strength": 77}, {"peaker": 0, "moving_average": 70, "time_stamp": 1596816902, "frequency": 4506500, "modulation": "NFM", "strength": 63}, {"peaker": 0, "moving_average": 70, "time_stamp": 1596816907, "frequency": 4506625, "modulation": "NFM", "strength": 71}, {"peaker": 0, "moving_average": 70, "time_stamp": 1596816912, "frequency": 4506750, "modulation": "NFM", "strength": 60}, {"peaker": 0, "moving_average": 70, "time_stamp": 1596816917, "frequency": 4506875, "modulation": "NFM", "strength": 61}, {"peaker": 0, "moving_average": 70, "time_stamp": 1596816922, "frequency": 4507000, "modulation": "NFM", "strength": 72}, {"peaker": 0, "moving_average": 70, "time_stamp": 1596816927, "frequency": 4507125, "modulation": "NFM", "strength": 71}, {"peaker": 0, "moving_average": 70, "time_stamp": 1596816932, "frequency": 4507250, "modulation": "NFM", "strength": 75}, {"peaker": 0, "moving_average": 70, "time_stamp": 1596816937, "frequency": 4507375, "modulation": "NFM", "strength": 71}, {"peaker": 0, "moving_average": 70, "time_stamp": 1596816942, "frequency": 4507500, "modulation": "NFM", "strength": 71}, {"peaker": 0, "moving_average": 70, "time_stamp": 1596816947, "frequency": 4507625, "modulation": "NFM", "strength": 70}, {"peaker": 0, "moving_average": 70, "time_stamp": 1596816953, "frequency": 4507750, "modulation": "NFM", "strength": 72}, {"peaker": 0, "moving_average": 70, "time_stamp": 1596816958, "frequency": 4507875, "modulation": "NFM", "strength": 70}, {"peaker": 0, "moving_average": 70, "time_stamp": 1596816963, "frequency": 4508000, "modulation": "NFM", "strength": 70}, {"peaker": 0, "moving_average": 70, "time_stamp": 1596816968, "frequency": 4508125, "modulation": "NFM", "strength": 68}, {"peaker": 0, "moving_average": 70, "time_stamp": 1596816973, "frequency": 4508250, "modulation": "NFM", "strength": 71}, {"peaker": 0, "moving_average": 70, "time_stamp": 1596816978, "frequency": 4508375, "modulation": "NFM", "strength": 71}, {"peaker": 0, "moving_average": 70, "time_stamp": 1596816983, "frequency": 4508500, "modulation": "NFM", "strength": 71}, {"peaker": 0, "moving_average": 70, "time_stamp": 1596816988, "frequency": 4508625, "modulation": "NFM", "strength": 69}, {"peaker": 0, "moving_average": 70, "time_stamp": 1596816993, "frequency": 4508750, "modulation": "NFM", "strength": 70}, {"peaker": 0, "moving_average": 70, "time_stamp": 1596816998, "frequency": 4508875, "modulation": "NFM", "strength": 81}, {"peaker": 0, "moving_average": 70, "time_stamp": 1596817003, "frequency": 4509000, "modulation": "NFM", "strength": 69}, {"peaker": 0, "moving_average": 70, "time_stamp": 1596817008, "frequency": 4509125, "modulation": "NFM", "strength": 71}, {"peaker": 0, "moving_average": 70, "time_stamp": 1596817013, "frequency": 4509250, "modulation": "NFM", "strength": 70}, {"peaker": 0, "moving_average": 70, "time_stamp": 1596817018, "frequency": 4509375, "modulation": "NFM", "strength": 70}, {"peaker": 0, "moving_average": 70, "time_stamp": 1596817023, "frequency": 4509500, "modulation": "NFM", "strength": 69}, {"peaker": 0, "moving_average": 70, "time_stamp": 1596817028, "frequency": 4509625, "modulation": "NFM", "strength": 77}, {"peaker": 0, "moving_average": 70, "time_stamp": 1596817033, "frequency": 4509750, "modulation": "NFM", "strength": 71}, {"peaker": 0, "moving_average": 70, "time_stamp": 1596817038, "frequency": 4509875, "modulation": "NFM", "strength": 73}, {"peaker": 0, "moving_average": 70, "time_stamp": 1596817043, "frequency": 4510000, "modulation": "NFM", "strength": 72}, {"peaker": 0, "moving_average": 70, "time_stamp": 1596817048, "frequency": 4510125, "modulation": "NFM", "strength": 73}, {"peaker": 0, "moving_average": 70, "time_stamp": 1596817053, "frequency": 4510250, "modulation": "NFM", "strength": 70}, {"peaker": 0, "moving_average": 70, "time_stamp": 1596817058, "frequency": 4510375, "modulation": "NFM", "strength": 63}, {"peaker": 0, "moving_average": 70, "time_stamp": 1596817063, "frequency": 4510500, "modulation": "NFM", "strength": 76}, {"peaker": 0, "moving_average": 70, "time_stamp": 1596817068, "frequency": 4510625, "modulation": "NFM", "strength": 74}, {"peaker": 0, "moving_average": 70, "time_stamp": 1596817073, "frequency": 4510750, "modulation": "NFM", "strength": 70}, {"peaker": 0, "moving_average": 70, "time_stamp": 1596817078, "frequency": 4510875, "modulation": "NFM", "strength": 62}, {"peaker": 0, "moving_average": 70, "time_stamp": 1596817083, "frequency": 4511000, "modulation": "NFM", "strength": 69}, {"peaker": 0, "moving_average": 70, "time_stamp": 1596817088, "frequency": 4511125, "modulation": "NFM", "strength": 83}, {"peaker": 0, "moving_average": 70, "time_stamp": 1596817093, "frequency": 4511250, "modulation": "NFM", "strength": 70}, {"peaker": 0, "moving_average": 70, "time_stamp": 1596817098, "frequency": 4511375, "modulation": "NFM", "strength": 68}, {"peaker": 0, "moving_average": 70, "time_stamp": 1596817104, "frequency": 4511500, "modulation": "NFM", "strength": 75}, {"peaker": 0, "moving_average": 70, "time_stamp": 1596817109, "frequency": 4511625, "modulation": "NFM", "strength": 71}, {"peaker": 0, "moving_average": 70, "time_stamp": 1596817114, "frequency": 4511750, "modulation": "NFM", "strength": 71}, {"peaker": 0, "moving_average": 70, "time_stamp": 1596817119, "frequency": 4511875, "modulation": "NFM", "strength": 63}, {"peaker": 0, "moving_average": 70, "time_stamp": 1596817124, "frequency": 4512000, "modulation": "NFM", "strength": 63}, {"peaker": 0, "moving_average": 70, "time_stamp": 1596817129, "frequency": 4512125, "modulation": "NFM", "strength": 70}, {"peaker": 0, "moving_average": 70, "time_stamp": 1596817134, "frequency": 4512250, "modulation": "NFM", "strength": 72}, {"peaker": 0, "moving_average": 70, "time_stamp": 1596817139, "frequency": 4512375, "modulation": "NFM", "strength": 72}, {"peaker": 0, "moving_average": 70, "time_stamp": 1596817144, "frequency": 4512500, "modulation": "NFM", "strength": 69}, {"peaker": 0, "moving_average": 70, "time_stamp": 1596817149, "frequency": 4512625, "modulation": "NFM", "strength": 71}, {"peaker": 0, "moving_average": 70, "time_stamp": 1596817154, "frequency": 4512750, "modulation": "NFM", "strength": 61}, {"peaker": 0, "moving_average": 70, "time_stamp": 1596817159, "frequency": 4512875, "modulation": "NFM", "strength": 71}, {"peaker": 0, "moving_average": 70, "time_stamp": 1596817164, "frequency": 4513000, "modulation": "NFM", "strength": 73}, {"peaker": 0, "moving_average": 70, "time_stamp": 1596817169, "frequency": 4513125, "modulation": "NFM", "strength": 63}, {"peaker": 0, "moving_average": 70, "time_stamp": 1596817174, "frequency": 4513250, "modulation": "NFM", "strength": 82}, {"peaker": 0, "moving_average": 70, "time_stamp": 1596817179, "frequency": 4513375, "modulation": "NFM", "strength": 81}, {"peaker": 0, "moving_average": 70, "time_stamp": 1596817184, "frequency": 4513500, "modulation": "NFM", "strength": 79}, {"peaker": 0, "moving_average": 70, "time_stamp": 1596817189, "frequency": 4513625, "modulation": "NFM", "strength": 66}, {"peaker": 0, "moving_average": 70, "time_stamp": 1596817194, "frequency": 4513750, "modulation": "NFM", "strength": 73}, {"peaker": 0, "moving_average": 70, "time_stamp": 1596817199, "frequency": 4513875, "modulation": "NFM", "strength": 67}, {"peaker": 0, "moving_average": 70, "time_stamp": 1596817204, "frequency": 4514000, "modulation": "NFM", "strength": 72}, {"peaker": 0, "moving_average": 70, "time_stamp": 1596817209, "frequency": 4514125, "modulation": "NFM", "strength": 70}, {"peaker": 0, "moving_average": 70, "time_stamp": 1596817214, "frequency": 4514250, "modulation": "NFM", "strength": 70}, {"peaker": 0, "moving_average": 70, "time_stamp": 1596817219, "frequency": 4514375, "modulation": "NFM", "strength": 72}, {"peaker": 0, "moving_average": 70, "time_stamp": 1596817224, "frequency": 4514500, "modulation": "NFM", "strength": 71}, {"peaker": 0, "moving_average": 70, "time_stamp": 1596817229, "frequency": 4514625, "modulation": "NFM", "strength": 76}, {"peaker": 0, "moving_average": 70, "time_stamp": 1596817234, "frequency": 4514750, "modulation": "NFM", "strength": 66}, {"peaker": 0, "moving_average": 70, "time_stamp": 1596817239, "frequency": 4514875, "modulation": "NFM", "strength": 70}, {"peaker": 0, "moving_average": 70, "time_stamp": 1596817244, "frequency": 4515000, "modulation": "NFM", "strength": 73}, {"peaker": 0, "moving_average": 70, "time_stamp": 1596817249, "frequency": 4515125, "modulation": "NFM", "strength": 65}, {"peaker": 0, "moving_average": 70, "time_stamp": 1596817255, "frequency": 4515250, "modulation": "NFM", "strength": 66}, {"peaker": 0, "moving_average": 70, "time_stamp": 1596817260, "frequency": 4515375, "modulation": "NFM", "strength": 71}, {"peaker": 0, "moving_average": 70, "time_stamp": 1596817265, "frequency": 4515500, "modulation": "NFM", "strength": 70}, {"peaker": 0, "moving_average": 70, "time_stamp": 1596817270, "frequency": 4515625, "modulation": "NFM", "strength": 81}, {"peaker": 0, "moving_average": 70, "time_stamp": 1596817275, "frequency": 4515750, "modulation": "NFM", "strength": 70}, {"peaker": 0, "moving_average": 70, "time_stamp": 1596817280, "frequency": 4515875, "modulation": "NFM", "strength": 66}, {"peaker": 0, "moving_average": 70, "time_stamp": 1596817285, "frequency": 4516000, "modulation": "NFM", "strength": 71}, {"peaker": 0, "moving_average": 71, "time_stamp": 1596817290, "frequency": 4516125, "modulation": "NFM", "strength": 80}, {"peaker": 0, "moving_average": 70, "time_stamp": 1596817295, "frequency": 4516250, "modulation": "NFM", "strength": 70}, {"peaker": 0, "moving_average": 70, "time_stamp": 1596817300, "frequency": 4516375, "modulation": "NFM", "strength": 72}, {"peaker": 0, "moving_average": 70, "time_stamp": 1596817305, "frequency": 4516500, "modulation": "NFM", "strength": 69}, {"peaker": 0, "moving_average": 70, "time_stamp": 1596817310, "frequency": 4516625, "modulation": "NFM", "strength": 73}, {"peaker": 0, "moving_average": 70, "time_stamp": 1596817315, "frequency": 4516750, "modulation": "NFM", "strength": 59}, {"peaker": 0, "moving_average": 70, "time_stamp": 1596817320, "frequency": 4516875, "modulation": "NFM", "strength": 64}, {"peaker": 0, "moving_average": 70, "time_stamp": 1596817325, "frequency": 4517000, "modulation": "NFM", "strength": 64}, {"peaker": 0, "moving_average": 70, "time_stamp": 1596817330, "frequency": 4517125, "modulation": "NFM", "strength": 72}, {"peaker": 0, "moving_average": 70, "time_stamp": 1596817335, "frequency": 4517250, "modulation": "NFM", "strength": 70}, {"peaker": 0, "moving_average": 70, "time_stamp": 1596817340, "frequency": 4517375, "modulation": "NFM", "strength": 71}, {"peaker": 0, "moving_average": 70, "time_stamp": 1596817345, "frequency": 4517500, "modulation": "NFM", "strength": 71}, {"peaker": 0, "moving_average": 70, "time_stamp": 1596817350, "frequency": 4517625, "modulation": "NFM", "strength": 73}, {"peaker": 0, "moving_average": 70, "time_stamp": 1596817355, "frequency": 4517750, "modulation": "NFM", "strength": 72}, {"peaker": 0, "moving_average": 70, "time_stamp": 1596817360, "frequency": 4517875, "modulation": "NFM", "strength": 79}, {"peaker": 0, "moving_average": 70, "time_stamp": 1596817365, "frequency": 4518000, "modulation": "NFM", "strength": 68}, {"peaker": 0, "moving_average": 70, "time_stamp": 1596817370, "frequency": 4518125, "modulation": "NFM", "strength": 76}, {"peaker": 0, "moving_average": 70, "time_stamp": 1596817375, "frequency": 4518250, "modulation": "NFM", "strength": 67}, {"peaker": 0, "moving_average": 70, "time_stamp": 1596817380, "frequency": 4518375, "modulation": "NFM", "strength": 71}, {"peaker": 0, "moving_average": 70, "time_stamp": 1596817385, "frequency": 4518500, "modulation": "NFM", "strength": 73}, {"peaker": 0, "moving_average": 70, "time_stamp": 1596817390, "frequency": 4518625, "modulation": "NFM", "strength": 68}, {"peaker": 0, "moving_average": 70, "time_stamp": 1596817395, "frequency": 4518750, "modulation": "NFM", "strength": 76}, {"peaker": 0, "moving_average": 70, "time_stamp": 1596817401, "frequency": 4518875, "modulation": "NFM", "strength": 71}, {"peaker": 0, "moving_average": 70, "time_stamp": 1596817406, "frequency": 4519000, "modulation": "NFM", "strength": 71}, {"peaker": 0, "moving_average": 70, "time_stamp": 1596817411, "frequency": 4519125, "modulation": "NFM", "strength": 70}, {"peaker": 0, "moving_average": 70, "time_stamp": 1596817416, "frequency": 4519250, "modulation": "NFM", "strength": 71}, {"peaker": 0, "moving_average": 70, "time_stamp": 1596817421, "frequency": 4519375, "modulation": "NFM", "strength": 59}, {"peaker": 0, "moving_average": 70, "time_stamp": 1596817426, "frequency": 4519500, "modulation": "NFM", "strength": 70}, {"peaker": 0, "moving_average": 70, "time_stamp": 1596817431, "frequency": 4519625, "modulation": "NFM", "strength": 69}, {"peaker": 0, "moving_average": 70, "time_stamp": 1596817436, "frequency": 4519750, "modulation": "NFM", "strength": 69}, {"peaker": 0, "moving_average": 70, "time_stamp": 1596817441, "frequency": 4519875, "modulation": "NFM", "strength": 70}, {"peaker": 0, "moving_average": 70, "time_stamp": 1596817446, "frequency": 4520000, "modulation": "NFM", "strength": 82}, {"peaker": 0, "moving_average": 70, "time_stamp": 1596817451, "frequency": 4520125, "modulation": "NFM", "strength": 70}, {"peaker": 0, "moving_average": 70, "time_stamp": 1596817456, "frequency": 4520250, "modulation": "NFM", "strength": 71}, {"peaker": 0, "moving_average": 70, "time_stamp": 1596817461, "frequency": 4520375, "modulation": "NFM", "strength": 65}, {"peaker": 0, "moving_average": 70, "time_stamp": 1596817466, "frequency": 4520500, "modulation": "NFM", "strength": 70}, {"peaker": 0, "moving_average": 70, "time_stamp": 1596817471, "frequency": 4520625, "modulation": "NFM", "strength": 72}, {"peaker": 0, "moving_average": 70, "time_stamp": 1596817476, "frequency": 4520750, "modulation": "NFM", "strength": 82}, {"peaker": 0, "moving_average": 70, "time_stamp": 1596817481, "frequency": 4520875, "modulation": "NFM", "strength": 75}, {"peaker": 0, "moving_average": 70, "time_stamp": 1596817486, "frequency": 4521000, "modulation": "NFM", "strength": 66}, {"peaker": 0, "moving_average": 70, "time_stamp": 1596817491, "frequency": 4521125, "modulation": "NFM", "strength": 71}, {"peaker": 0, "moving_average": 70, "time_stamp": 1596817496, "frequency": 4521250, "modulation": "NFM", "strength": 79}, {"peaker": 0, "moving_average": 70, "time_stamp": 1596817501, "frequency": 4521375, "modulation": "NFM", "strength": 69}, {"peaker": 0, "moving_average": 70, "time_stamp": 1596817506, "frequency": 4521500, "modulation": "NFM", "strength": 69}, {"peaker": 0, "moving_average": 71, "time_stamp": 1596817511, "frequency": 4521625, "modulation": "NFM", "strength": 82}, {"peaker": 0, "moving_average": 71, "time_stamp": 1596817516, "frequency": 4521750, "modulation": "NFM", "strength": 70}, {"peaker": 0, "moving_average": 71, "time_stamp": 1596817521, "frequency": 4521875, "modulation": "NFM", "strength": 68}, {"peaker": 0, "moving_average": 71, "time_stamp": 1596817526, "frequency": 4522000, "modulation": "NFM", "strength": 70}, {"peaker": 0, "moving_average": 71, "time_stamp": 1596817531, "frequency": 4522125, "modulation": "NFM", "strength": 71}, {"peaker": 0, "moving_average": 71, "time_stamp": 1596817536, "frequency": 4522250, "modulation": "NFM", "strength": 76}, {"peaker": 0, "moving_average": 70, "time_stamp": 1596817541, "frequency": 4522375, "modulation": "NFM", "strength": 60}, {"peaker": 0, "moving_average": 70, "time_stamp": 1596817546, "frequency": 4522500, "modulation": "NFM", "strength": 73}, {"peaker": 0, "moving_average": 71, "time_stamp": 1596817552, "frequency": 4522625, "modulation": "NFM", "strength": 83}, {"peaker": 0, "moving_average": 70, "time_stamp": 1596817557, "frequency": 4522750, "modulation": "NFM", "strength": 61}, {"peaker": 0, "moving_average": 70, "time_stamp": 1596817562, "frequency": 4522875, "modulation": "NFM", "strength": 77}, {"peaker": 0, "moving_average": 70, "time_stamp": 1596817567, "frequency": 4523000, "modulation": "NFM", "strength": 72}, {"peaker": 0, "moving_average": 70, "time_stamp": 1596817572, "frequency": 4523125, "modulation": "NFM", "strength": 71}, {"peaker": 0, "moving_average": 71, "time_stamp": 1596817577, "frequency": 4523250, "modulation": "NFM", "strength": 74}, {"peaker": 0, "moving_average": 70, "time_stamp": 1596817582, "frequency": 4523375, "modulation": "NFM", "strength": 64}, {"peaker": 0, "moving_average": 70, "time_stamp": 1596817587, "frequency": 4523500, "modulation": "NFM", "strength": 65}, {"peaker": 0, "moving_average": 70, "time_stamp": 1596817592, "frequency": 4523625, "modulation": "NFM", "strength": 71}, {"peaker": 0, "moving_average": 70, "time_stamp": 1596817597, "frequency": 4523750, "modulation": "NFM", "strength": 68}, {"peaker": 0, "moving_average": 70, "time_stamp": 1596817602, "frequency": 4523875, "modulation": "NFM", "strength": 71}, {"peaker": 0, "moving_average": 70, "time_stamp": 1596817607, "frequency": 4524000, "modulation": "NFM", "strength": 70}, {"peaker": 0, "moving_average": 70, "time_stamp": 1596817612, "frequency": 4524125, "modulation": "NFM", "strength": 72}, {"peaker": 0, "moving_average": 70, "time_stamp": 1596817617, "frequency": 4524250, "modulation": "NFM", "strength": 71}, {"peaker": 0, "moving_average": 70, "time_stamp": 1596817622, "frequency": 4524375, "modulation": "NFM", "strength": 73}, {"peaker": 0, "moving_average": 70, "time_stamp": 1596817627, "frequency": 4524500, "modulation": "NFM", "strength": 71}, {"peaker": 0, "moving_average": 71, "time_stamp": 1596817632, "frequency": 4524625, "modulation": "NFM", "strength": 82}, {"peaker": 0, "moving_average": 71, "time_stamp": 1596817637, "frequency": 4524750, "modulation": "NFM", "strength": 85}, {"peaker": 0, "moving_average": 71, "time_stamp": 1596817642, "frequency": 4524875, "modulation": "NFM", "strength": 82}, {"peaker": 0, "moving_average": 71, "time_stamp": 1596817647, "frequency": 4525000, "modulation": "NFM", "strength": 68}, {"peaker": 0, "moving_average": 71, "time_stamp": 1596817652, "frequency": 4525125, "modulation": "NFM", "strength": 72}, {"peaker": 0, "moving_average": 71, "time_stamp": 1596817657, "frequency": 4525250, "modulation": "NFM", "strength": 72}, {"peaker": 0, "moving_average": 71, "time_stamp": 1596817662, "frequency": 4525375, "modulation": "NFM", "strength": 74}, {"peaker": 0, "moving_average": 71, "time_stamp": 1596817667, "frequency": 4525500, "modulation": "NFM", "strength": 71}, {"peaker": 0, "moving_average": 71, "time_stamp": 1596817672, "frequency": 4525625, "modulation": "NFM", "strength": 70}, {"peaker": 0, "moving_average": 71, "time_stamp": 1596817677, "frequency": 4525750, "modulation": "NFM", "strength": 80}, {"peaker": 0, "moving_average": 71, "time_stamp": 1596817682, "frequency": 4525875, "modulation": "NFM", "strength": 71}, {"peaker": 0, "moving_average": 71, "time_stamp": 1596817687, "frequency": 4526000, "modulation": "NFM", "strength": 71}, {"peaker": 0, "moving_average": 71, "time_stamp": 1596817692, "frequency": 4526125, "modulation": "NFM", "strength": 71}, {"peaker": 0, "moving_average": 71, "time_stamp": 1596817697, "frequency": 4526250, "modulation": "NFM", "strength": 71}, {"peaker": 0, "moving_average": 71, "time_stamp": 1596817703, "frequency": 4526375, "modulation": "NFM", "strength": 70}, {"peaker": 0, "moving_average": 71, "time_stamp": 1596817708, "frequency": 4526500, "modulation": "NFM", "strength": 63}, {"peaker": 0, "moving_average": 71, "time_stamp": 1596817713, "frequency": 4526625, "modulation": "NFM", "strength": 70}, {"peaker": 0, "moving_average": 71, "time_stamp": 1596817718, "frequency": 4526750, "modulation": "NFM", "strength": 68}, {"peaker": 0, "moving_average": 71, "time_stamp": 1596817723, "frequency": 4526875, "modulation": "NFM", "strength": 82}, {"peaker": 0, "moving_average": 71, "time_stamp": 1596817728, "frequency": 4527000, "modulation": "NFM", "strength": 69}, {"peaker": 0, "moving_average": 71, "time_stamp": 1596817733, "frequency": 4527125, "modulation": "NFM", "strength": 71}, {"peaker": 0, "moving_average": 71, "time_stamp": 1596817738, "frequency": 4527250, "modulation": "NFM", "strength": 69}, {"peaker": 0, "moving_average": 71, "time_stamp": 1596817743, "frequency": 4527375, "modulation": "NFM", "strength": 72}, {"peaker": 0, "moving_average": 71, "time_stamp": 1596817748, "frequency": 4527500, "modulation": "NFM", "strength": 70}, {"peaker": 0, "moving_average": 71, "time_stamp": 1596817753, "frequency": 4527625, "modulation": "NFM", "strength": 78}, {"peaker": 0, "moving_average": 71, "time_stamp": 1596817758, "frequency": 4527750, "modulation": "NFM", "strength": 70}, {"peaker": 0, "moving_average": 71, "time_stamp": 1596817763, "frequency": 4527875, "modulation": "NFM", "strength": 70}, {"peaker": 0, "moving_average": 71, "time_stamp": 1596817768, "frequency": 4528000, "modulation": "NFM", "strength": 70}, {"peaker": 0, "moving_average": 71, "time_stamp": 1596817773, "frequency": 4528125, "modulation": "NFM", "strength": 74}, {"peaker": 0, "moving_average": 71, "time_stamp": 1596817778, "frequency": 4528250, "modulation": "NFM", "strength": 74}, {"peaker": 0, "moving_average": 71, "time_stamp": 1596817783, "frequency": 4528375, "modulation": "NFM", "strength": 72}, {"peaker": 0, "moving_average": 72, "time_stamp": 1596817788, "frequency": 4528500, "modulation": "NFM", "strength": 83}, {"peaker": 0, "moving_average": 72, "time_stamp": 1596817793, "frequency": 4528625, "modulation": "NFM", "strength": 67}, {"peaker": 0, "moving_average": 71, "time_stamp": 1596817798, "frequency": 4528750, "modulation": "NFM", "strength": 64}, {"peaker": 0, "moving_average": 71, "time_stamp": 1596817803, "frequency": 4528875, "modulation": "NFM", "strength": 70}, {"peaker": 0, "moving_average": 71, "time_stamp": 1596817808, "frequency": 4529000, "modulation": "NFM", "strength": 71}, {"peaker": 0, "moving_average": 71, "time_stamp": 1596817813, "frequency": 4529125, "modulation": "NFM", "strength": 63}, {"peaker": 0, "moving_average": 71, "time_stamp": 1596817818, "frequency": 4529250, "modulation": "NFM", "strength": 60}, {"peaker": 0, "moving_average": 71, "time_stamp": 1596817823, "frequency": 4529375, "modulation": "NFM", "strength": 69}, {"peaker": 0, "moving_average": 71, "time_stamp": 1596817828, "frequency": 4529500, "modulation": "NFM", "strength": 68}, {"peaker": 0, "moving_average": 71, "time_stamp": 1596817833, "frequency": 4529625, "modulation": "NFM", "strength": 68}, {"peaker": 0, "moving_average": 71, "time_stamp": 1596817838, "frequency": 4529750, "modulation": "NFM", "strength": 69}, {"peaker": 0, "moving_average": 71, "time_stamp": 1596817843, "frequency": 4529875, "modulation": "NFM", "strength": 71}, {"peaker": 0, "moving_average": 71, "time_stamp": 1596817848, "frequency": 4530000, "modulation": "NFM", "strength": 61}, {"peaker": 0, "moving_average": 71, "time_stamp": 1596817854, "frequency": 4530125, "modulation": "NFM", "strength": 70}, {"peaker": 0, "moving_average": 71, "time_stamp": 1596817859, "frequency": 4530250, "modulation": "NFM", "strength": 69}, {"peaker": 0, "moving_average": 71, "time_stamp": 1596817864, "frequency": 4530375, "modulation": "NFM", "strength": 72}, {"peaker": 0, "moving_average": 71, "time_stamp": 1596817869, "frequency": 4530500, "modulation": "NFM", "strength": 72}, {"peaker": 0, "moving_average": 71, "time_stamp": 1596817874, "frequency": 4530625, "modulation": "NFM", "strength": 72}, {"peaker": 0, "moving_average": 71, "time_stamp": 1596817879, "frequency": 4530750, "modulation": "NFM", "strength": 70}, {"peaker": 0, "moving_average": 71, "time_stamp": 1596817884, "frequency": 4530875, "modulation": "NFM", "strength": 68}, {"peaker": 0, "moving_average": 71, "time_stamp": 1596817889, "frequency": 4531000, "modulation": "NFM", "strength": 70}, {"peaker": 0, "moving_average": 71, "time_stamp": 1596817894, "frequency": 4531125, "modulation": "NFM", "strength": 71}, {"peaker": 0, "moving_average": 70, "time_stamp": 1596817899, "frequency": 4531250, "modulation": "NFM", "strength": 68}, {"peaker": 0, "moving_average": 71, "time_stamp": 1596817904, "frequency": 4531375, "modulation": "NFM", "strength": 73}, {"peaker": 0, "moving_average": 71, "time_stamp": 1596817909, "frequency": 4531500, "modulation": "NFM", "strength": 68}, {"peaker": 0, "moving_average": 70, "time_stamp": 1596817914, "frequency": 4531625, "modulation": "NFM", "strength": 58}, {"peaker": 0, "moving_average": 70, "time_stamp": 1596817919, "frequency": 4531750, "modulation": "NFM", "strength": 68}, {"peaker": 0, "moving_average": 70, "time_stamp": 1596817924, "frequency": 4531875, "modulation": "NFM", "strength": 68}, {"peaker": 0, "moving_average": 70, "time_stamp": 1596817929, "frequency": 4532000, "modulation": "NFM", "strength": 73}, {"peaker": 0, "moving_average": 70, "time_stamp": 1596817934, "frequency": 4532125, "modulation": "NFM", "strength": 69}, {"peaker": 0, "moving_average": 70, "time_stamp": 1596817939, "frequency": 4532250, "modulation": "NFM", "strength": 68}, {"peaker": 0, "moving_average": 70, "time_stamp": 1596817944, "frequency": 4532375, "modulation": "NFM", "strength": 67}, {"peaker": 0, "moving_average": 70, "time_stamp": 1596817949, "frequency": 4532500, "modulation": "NFM", "strength": 83}, {"peaker": 0, "moving_average": 70, "time_stamp": 1596817954, "frequency": 4532625, "modulation": "NFM", "strength": 70}, {"peaker": 0, "moving_average": 70, "time_stamp": 1596817959, "frequency": 4532750, "modulation": "NFM", "strength": 62}, {"peaker": 0, "moving_average": 70, "time_stamp": 1596817964, "frequency": 4532875, "modulation": "NFM", "strength": 69}, {"peaker": 0, "moving_average": 70, "time_stamp": 1596817969, "frequency": 4533000, "modulation": "NFM", "strength": 72}, {"peaker": 0, "moving_average": 70, "time_stamp": 1596817974, "frequency": 4533125, "modulation": "NFM", "strength": 67}, {"peaker": 0, "moving_average": 70, "time_stamp": 1596817979, "frequency": 4533250, "modulation": "NFM", "strength": 62}, {"peaker": 0, "moving_average": 70, "time_stamp": 1596817984, "frequency": 4533375, "modulation": "NFM", "strength": 67}, {"peaker": 0, "moving_average": 70, "time_stamp": 1596817989, "frequency": 4533500, "modulation": "NFM", "strength": 71}, {"peaker": 0, "moving_average": 70, "time_stamp": 1596817994, "frequency": 4533625, "modulation": "NFM", "strength": 69}, {"peaker": 0, "moving_average": 70, "time_stamp": 1596817999, "frequency": 4533750, "modulation": "NFM", "strength": 83}, {"peaker": 0, "moving_average": 70, "time_stamp": 1596818005, "frequency": 4533875, "modulation": "NFM", "strength": 67}, {"peaker": 0, "moving_average": 70, "time_stamp": 1596818010, "frequency": 4534000, "modulation": "NFM", "strength": 65}, {"peaker": 0, "moving_average": 69, "time_stamp": 1596818015, "frequency": 4534125, "modulation": "NFM", "strength": 71}, {"peaker": 0, "moving_average": 69, "time_stamp": 1596818020, "frequency": 4534250, "modulation": "NFM", "strength": 61}, {"peaker": 0, "moving_average": 69, "time_stamp": 1596818025, "frequency": 4534375, "modulation": "NFM", "strength": 68}, {"peaker": 0, "moving_average": 69, "time_stamp": 1596818030, "frequency": 4534500, "modulation": "NFM", "strength": 68}, {"peaker": 0, "moving_average": 69, "time_stamp": 1596818035, "frequency": 4534625, "modulation": "NFM", "strength": 73}, {"peaker": 0, "moving_average": 69, "time_stamp": 1596818040, "frequency": 4534750, "modulation": "NFM", "strength": 71}, {"peaker": 0, "moving_average": 69, "time_stamp": 1596818045, "frequency": 4534875, "modulation": "NFM", "strength": 71}, {"peaker": 0, "moving_average": 69, "time_stamp": 1596818050, "frequency": 4535000, "modulation": "NFM", "strength": 80}, {"peaker": 0, "moving_average": 69, "time_stamp": 1596818055, "frequency": 4535125, "modulation": "NFM", "strength": 63}, {"peaker": 0, "moving_average": 69, "time_stamp": 1596818060, "frequency": 4535250, "modulation": "NFM", "strength": 69}, {"peaker": 0, "moving_average": 69, "time_stamp": 1596818065, "frequency": 4535375, "modulation": "NFM", "strength": 71}, {"peaker": 0, "moving_average": 69, "time_stamp": 1596818070, "frequency": 4535500, "modulation": "NFM", "strength": 61}, {"peaker": 0, "moving_average": 69, "time_stamp": 1596818075, "frequency": 4535625, "modulation": "NFM", "strength": 71}, {"peaker": 0, "moving_average": 69, "time_stamp": 1596818080, "frequency": 4535750, "modulation": "NFM", "strength": 69}, {"peaker": 0, "moving_average": 69, "time_stamp": 1596818085, "frequency": 4535875, "modulation": "NFM", "strength": 74}, {"peaker": 0, "moving_average": 69, "time_stamp": 1596818090, "frequency": 4536000, "modulation": "NFM", "strength": 74}, {"peaker": 0, "moving_average": 69, "time_stamp": 1596818095, "frequency": 4536125, "modulation": "NFM", "strength": 74}, {"peaker": 0, "moving_average": 69, "time_stamp": 1596818100, "frequency": 4536250, "modulation": "NFM", "strength": 66}, {"peaker": 0, "moving_average": 69, "time_stamp": 1596818105, "frequency": 4536375, "modulation": "NFM", "strength": 64}, {"peaker": 0, "moving_average": 69, "time_stamp": 1596818110, "frequency": 4536500, "modulation": "NFM", "strength": 72}, {"peaker": 0, "moving_average": 69, "time_stamp": 1596818115, "frequency": 4536625, "modulation": "NFM", "strength": 66}, {"peaker": 0, "moving_average": 69, "time_stamp": 1596818120, "frequency": 4536750, "modulation": "NFM", "strength": 65}, {"peaker": 0, "moving_average": 69, "time_stamp": 1596818125, "frequency": 4536875, "modulation": "NFM", "strength": 79}, {"peaker": 0, "moving_average": 69, "time_stamp": 1596818130, "frequency": 4537000, "modulation": "NFM", "strength": 77}, {"peaker": 0, "moving_average": 69, "time_stamp": 1596818135, "frequency": 4537125, "modulation": "NFM", "strength": 58}, {"peaker": 0, "moving_average": 69, "time_stamp": 1596818140, "frequency": 4537250, "modulation": "NFM", "strength": 69}, {"peaker": 0, "moving_average": 69, "time_stamp": 1596818145, "frequency": 4537375, "modulation": "NFM", "strength": 70}, {"peaker": 0, "moving_average": 68, "time_stamp": 1596818150, "frequency": 4537500, "modulation": "NFM", "strength": 70}, {"peaker": 0, "moving_average": 69, "time_stamp": 1596818156, "frequency": 4537625, "modulation": "NFM", "strength": 77}, {"peaker": 0, "moving_average": 69, "time_stamp": 1596818161, "frequency": 4537750, "modulation": "NFM", "strength": 71}, {"peaker": 0, "moving_average": 69, "time_stamp": 1596818166, "frequency": 4537875, "modulation": "NFM", "strength": 69}, {"peaker": 0, "moving_average": 69, "time_stamp": 1596818171, "frequency": 4538000, "modulation": "NFM", "strength": 75}, {"peaker": 0, "moving_average": 69, "time_stamp": 1596818176, "frequency": 4538125, "modulation": "NFM", "strength": 72}, {"peaker": 0, "moving_average": 69, "time_stamp": 1596818181, "frequency": 4538250, "modulation": "NFM", "strength": 64}, {"peaker": 0, "moving_average": 69, "time_stamp": 1596818186, "frequency": 4538375, "modulation": "NFM", "strength": 67}, {"peaker": 0, "moving_average": 69, "time_stamp": 1596818191, "frequency": 4538500, "modulation": "NFM", "strength": 76}, {"peaker": 0, "moving_average": 69, "time_stamp": 1596818196, "frequency": 4538625, "modulation": "NFM", "strength": 71}, {"peaker": 0, "moving_average": 69, "time_stamp": 1596818201, "frequency": 4538750, "modulation": "NFM", "strength": 70}, {"peaker": 0, "moving_average": 69, "time_stamp": 1596818206, "frequency": 4538875, "modulation": "NFM", "strength": 70}, {"peaker": 0, "moving_average": 69, "time_stamp": 1596818211, "frequency": 4539000, "modulation": "NFM", "strength": 74}, {"peaker": 0, "moving_average": 69, "time_stamp": 1596818216, "frequency": 4539125, "modulation": "NFM", "strength": 68}, {"peaker": 0, "moving_average": 69, "time_stamp": 1596818221, "frequency": 4539250, "modulation": "NFM", "strength": 71}, {"peaker": 0, "moving_average": 69, "time_stamp": 1596818226, "frequency": 4539375, "modulation": "NFM", "strength": 75}, {"peaker": 0, "moving_average": 69, "time_stamp": 1596818231, "frequency": 4539500, "modulation": "NFM", "strength": 70}, {"peaker": 0, "moving_average": 69, "time_stamp": 1596818236, "frequency": 4539625, "modulation": "NFM", "strength": 69}, {"peaker": 0, "moving_average": 69, "time_stamp": 1596818241, "frequency": 4539750, "modulation": "NFM", "strength": 73}, {"peaker": 0, "moving_average": 69, "time_stamp": 1596818246, "frequency": 4539875, "modulation": "NFM", "strength": 69}, {"peaker": 0, "moving_average": 69, "time_stamp": 1596818251, "frequency": 4540000, "modulation": "NFM", "strength": 77}, {"peaker": 0, "moving_average": 69, "time_stamp": 1596818256, "frequency": 4540125, "modulation": "NFM", "strength": 69}, {"peaker": 0, "moving_average": 69, "time_stamp": 1596818261, "frequency": 4540250, "modulation": "NFM", "strength": 75}, {"peaker": 0, "moving_average": 69, "time_stamp": 1596818266, "frequency": 4540375, "modulation": "NFM", "strength": 70}, {"peaker": 0, "moving_average": 69, "time_stamp": 1596818271, "frequency": 4540500, "modulation": "NFM", "strength": 70}, {"peaker": 0, "moving_average": 70, "time_stamp": 1596818276, "frequency": 4540625, "modulation": "NFM", "strength": 77}, {"peaker": 0, "moving_average": 70, "time_stamp": 1596818281, "frequency": 4540750, "modulation": "NFM", "strength": 68}, {"peaker": 0, "moving_average": 70, "time_stamp": 1596818286, "frequency": 4540875, "modulation": "NFM", "strength": 69}, {"peaker": 1, "moving_average": 70, "time_stamp": 1596818291, "frequency": 4541000, "modulation": "NFM", "strength": 97}, {"peaker": 1, "moving_average": 70, "time_stamp": 1596818296, "frequency": 4541125, "modulation": "NFM", "strength": 90}, {"peaker": 0, "moving_average": 71, "time_stamp": 1596818301, "frequency": 4541250, "modulation": "NFM", "strength": 82}, {"peaker": 0, "moving_average": 71, "time_stamp": 1596818307, "frequency": 4541375, "modulation": "NFM", "strength": 70}, {"peaker": 0, "moving_average": 70, "time_stamp": 1596818312, "frequency": 4541500, "modulation": "NFM", "strength": 70}, {"peaker": 0, "moving_average": 70, "time_stamp": 1596818317, "frequency": 4541625, "modulation": "NFM", "strength": 70}, {"peaker": 0, "moving_average": 70, "time_stamp": 1596818322, "frequency": 4541750, "modulation": "NFM", "strength": 57}, {"peaker": 0, "moving_average": 70, "time_stamp": 1596818327, "frequency": 4541875, "modulation": "NFM", "strength": 73}, {"peaker": 0, "moving_average": 71, "time_stamp": 1596818332, "frequency": 4542000, "modulation": "NFM", "strength": 85}, {"peaker": 0, "moving_average": 71, "time_stamp": 1596818337, "frequency": 4542125, "modulation": "NFM", "strength": 68}, {"peaker": 0, "moving_average": 71, "time_stamp": 1596818342, "frequency": 4542250, "modulation": "NFM", "strength": 69}, {"peaker": 0, "moving_average": 71, "time_stamp": 1596818347, "frequency": 4542375, "modulation": "NFM", "strength": 60}, {"peaker": 0, "moving_average": 71, "time_stamp": 1596818352, "frequency": 4542500, "modulation": "NFM", "strength": 75}, {"peaker": 0, "moving_average": 71, "time_stamp": 1596818357, "frequency": 4542625, "modulation": "NFM", "strength": 72}, {"peaker": 0, "moving_average": 70, "time_stamp": 1596818362, "frequency": 4542750, "modulation": "NFM", "strength": 59}, {"peaker": 0, "moving_average": 70, "time_stamp": 1596818367, "frequency": 4542875, "modulation": "NFM", "strength": 70}, {"peaker": 0, "moving_average": 70, "time_stamp": 1596818372, "frequency": 4543000, "modulation": "NFM", "strength": 65}, {"peaker": 0, "moving_average": 70, "time_stamp": 1596818377, "frequency": 4543125, "modulation": "NFM", "strength": 69}, {"peaker": 0, "moving_average": 70, "time_stamp": 1596818382, "frequency": 4543250, "modulation": "NFM", "strength": 69}, {"peaker": 0, "moving_average": 71, "time_stamp": 1596818387, "frequency": 4543375, "modulation": "NFM", "strength": 72}, {"peaker": 0, "moving_average": 71, "time_stamp": 1596818392, "frequency": 4543500, "modulation": "NFM", "strength": 71}, {"peaker": 0, "moving_average": 71, "time_stamp": 1596818397, "frequency": 4543625, "modulation": "NFM", "strength": 70}, {"peaker": 0, "moving_average": 70, "time_stamp": 1596818402, "frequency": 4543750, "modulation": "NFM", "strength": 63}, {"peaker": 0, "moving_average": 70, "time_stamp": 1596818407, "frequency": 4543875, "modulation": "NFM", "strength": 66}, {"peaker": 0, "moving_average": 70, "time_stamp": 1596818412, "frequency": 4544000, "modulation": "NFM", "strength": 74}, {"peaker": 0, "moving_average": 70, "time_stamp": 1596818417, "frequency": 4544125, "modulation": "NFM", "strength": 75}, {"peaker": 0, "moving_average": 70, "time_stamp": 1596818422, "frequency": 4544250, "modulation": "NFM", "strength": 70}, {"peaker": 1, "moving_average": 72, "time_stamp": 1596818427, "frequency": 4544375, "modulation": "NFM", "strength": 155}, {"peaker": 1, "moving_average": 73, "time_stamp": 1596818432, "frequency": 4544500, "modulation": "NFM", "strength": 136}, {"peaker": 0, "moving_average": 73, "time_stamp": 1596818437, "frequency": 4544625, "modulation": "NFM", "strength": 72}, {"peaker": 0, "moving_average": 73, "time_stamp": 1596818442, "frequency": 4544750, "modulation": "NFM", "strength": 61}, {"peaker": 1, "moving_average": 73, "time_stamp": 1596818447, "frequency": 4544875, "modulation": "NFM", "strength": 122}, {"peaker": 1, "moving_average": 74, "time_stamp": 1596818453, "frequency": 4545000, "modulation": "NFM", "strength": 95}, {"peaker": 0, "moving_average": 74, "time_stamp": 1596818458, "frequency": 4545125, "modulation": "NFM", "strength": 75}, {"peaker": 0, "moving_average": 74, "time_stamp": 1596818463, "frequency": 4545250, "modulation": "NFM", "strength": 71}, {"peaker": 0, "moving_average": 74, "time_stamp": 1596818468, "frequency": 4545375, "modulation": "NFM", "strength": 69}, {"peaker": 0, "moving_average": 74, "time_stamp": 1596818473, "frequency": 4545500, "modulation": "NFM", "strength": 68}, {"peaker": 0, "moving_average": 74, "time_stamp": 1596818478, "frequency": 4545625, "modulation": "NFM", "strength": 76}, {"peaker": 0, "moving_average": 74, "time_stamp": 1596818483, "frequency": 4545750, "modulation": "NFM", "strength": 71}, {"peaker": 0, "moving_average": 74, "time_stamp": 1596818488, "frequency": 4545875, "modulation": "NFM", "strength": 78}, {"peaker": 0, "moving_average": 74, "time_stamp": 1596818493, "frequency": 4546000, "modulation": "NFM", "strength": 71}, {"peaker": 0, "moving_average": 74, "time_stamp": 1596818498, "frequency": 4546125, "modulation": "NFM", "strength": 77}, {"peaker": 0, "moving_average": 74, "time_stamp": 1596818503, "frequency": 4546250, "modulation": "NFM", "strength": 76}, {"peaker": 1, "moving_average": 75, "time_stamp": 1596818508, "frequency": 4546375, "modulation": "NFM", "strength": 154}, {"peaker": 1, "moving_average": 77, "time_stamp": 1596818513, "frequency": 4546500, "modulation": "NFM", "strength": 160}, {"peaker": 0, "moving_average": 76, "time_stamp": 1596818518, "frequency": 4546625, "modulation": "NFM", "strength": 74}, {"peaker": 0, "moving_average": 76, "time_stamp": 1596818523, "frequency": 4546750, "modulation": "NFM", "strength": 68}, {"peaker": 0, "moving_average": 76, "time_stamp": 1596818528, "frequency": 4546875, "modulation": "NFM", "strength": 66}, {"peaker": 0, "moving_average": 76, "time_stamp": 1596818533, "frequency": 4547000, "modulation": "NFM", "strength": 69}, {"peaker": 0, "moving_average": 76, "time_stamp": 1596818538, "frequency": 4547125, "modulation": "NFM", "strength": 70}, {"peaker": 0, "moving_average": 76, "time_stamp": 1596818543, "frequency": 4547250, "modulation": "NFM", "strength": 61}, {"peaker": 0, "moving_average": 76, "time_stamp": 1596818548, "frequency": 4547375, "modulation": "NFM", "strength": 70}, {"peaker": 0, "moving_average": 76, "time_stamp": 1596818553, "frequency": 4547500, "modulation": "NFM", "strength": 68}, {"peaker": 0, "moving_average": 76, "time_stamp": 1596818558, "frequency": 4547625, "modulation": "NFM", "strength": 72}, {"peaker": 0, "moving_average": 76, "time_stamp": 1596818563, "frequency": 4547750, "modulation": "NFM", "strength": 81}, {"peaker": 0, "moving_average": 76, "time_stamp": 1596818568, "frequency": 4547875, "modulation": "NFM", "strength": 68}, {"peaker": 0, "moving_average": 76, "time_stamp": 1596818573, "frequency": 4548000, "modulation": "NFM", "strength": 66}, {"peaker": 0, "moving_average": 76, "time_stamp": 1596818578, "frequency": 4548125, "modulation": "NFM", "strength": 62}, {"peaker": 0, "moving_average": 76, "time_stamp": 1596818583, "frequency": 4548250, "modulation": "NFM", "strength": 71}, {"peaker": 0, "moving_average": 76, "time_stamp": 1596818588, "frequency": 4548375, "modulation": "NFM", "strength": 71}, {"peaker": 0, "moving_average": 76, "time_stamp": 1596818593, "frequency": 4548500, "modulation": "NFM", "strength": 79}, {"peaker": 0, "moving_average": 76, "time_stamp": 1596818598, "frequency": 4548625, "modulation": "NFM", "strength": 69}, {"peaker": 0, "moving_average": 76, "time_stamp": 1596818604, "frequency": 4548750, "modulation": "NFM", "strength": 71}, {"peaker": 0, "moving_average": 76, "time_stamp": 1596818609, "frequency": 4548875, "modulation": "NFM", "strength": 82}, {"peaker": 0, "moving_average": 76, "time_stamp": 1596818614, "frequency": 4549000, "modulation": "NFM", "strength": 70}, {"peaker": 0, "moving_average": 76, "time_stamp": 1596818619, "frequency": 4549125, "modulation": "NFM", "strength": 68}, {"peaker": 0, "moving_average": 76, "time_stamp": 1596818624, "frequency": 4549250, "modulation": "NFM", "strength": 79}, {"peaker": 0, "moving_average": 76, "time_stamp": 1596818629, "frequency": 4549375, "modulation": "NFM", "strength": 71}, {"peaker": 0, "moving_average": 76, "time_stamp": 1596818634, "frequency": 4549500, "modulation": "NFM", "strength": 82}, {"peaker": 0, "moving_average": 76, "time_stamp": 1596818639, "frequency": 4549625, "modulation": "NFM", "strength": 70}, {"peaker": 0, "moving_average": 76, "time_stamp": 1596818644, "frequency": 4549750, "modulation": "NFM", "strength": 68}, {"peaker": 0, "moving_average": 76, "time_stamp": 1596818649, "frequency": 4549875, "modulation": "NFM", "strength": 71}, {"peaker": 0, "moving_average": 76, "time_stamp": 1596818654, "frequency": 4550000, "modulation": "NFM", "strength": 71}], "sortie": "a07e6247-2513-4642-91af-49dee65a94bc", "version": 1}